Workbook

Sheet TD
A3: Suma de Neto | B3: Etiquetas de columna
A4: Etiquetas de fila | B4: ENERO | C4: FEBRERO | D4: MARZO | F4: VARIACIÓN | G4: VAR. %
A5: ALIANZA FIDUCIARIA S.A | D5: 1423500 | F5: =+D5-C5 -> 1423500 | G5: =+IFERROR(D5/C5-1,0) -> 0
A6: BANCO AGRARIO DE COLOMBIA | B6: 2190 | C6: 20604 | F6: =+D6-C6 -> -20604 | G6: =+IFERROR(D6/C6-1,0) -> -1
A7: BANCO AGRARIO DE COLOMBIA S.A | C7: 11424.49 | D7: 12052 | F7: =+D7-C7 -> 627.51 | G7: =+IFERROR(D7/C7-1,0) -> 0.054926741
A8: BANCO DE BOGOTA | B8: 4303049 | C8: 1675065 | D8: 1802342 | F8: =+D8-C8 -> 127277 | G8: =+IFERROR(D8/C8-1,0) -> 0.07598332
A9: BANCO POPULAR | B9: 2650 | C9: 0 | D9: 15900 | F9: =+D9-C9 -> 15900 | G9: =+IFERROR(D9/C9-1,0) -> 0
A10: BANCOLOMBIA | B10: 4739977 | C10: 4209166.1 | D10: 40781.32 | F10: =+D10-C10 -> -4168384.8 | G10: =+IFERROR(D10/C10-1,0) -> -0.99031131
A11: BANCOLOMBIA PANAMA | B11: 514829.43 | C11: 284369.99 | D11: 475395.51 | F11: =+D11-C11 -> 191025.52 | G11: =+IFERROR(D11/C11-1,0) -> 0.67174993
A12: BBVA COLOMBIA S.A. | B12: 43927682 | C12: 51359812 | D12: 1.0580054e+08 | F12: =+D12-C12 -> 54440725 | G12: =+IFERROR(D12/C12-1,0) -> 1.0599868
A13: COMISIONES FACTORING BBVA BAVARIA-GOLOSINAS TRULULU-SUPER DE ALIMENTOS | D13: 59241903 | F13: =+D13-C13 -> 59241903 | G13: =+IFERROR(D13/C13-1,0) -> 0
A14: DEVOLUCION DE DSF - GASTOS BANCARIOS MES DE ENERO 2025 | C14: -43927682 | F14: =+D14-C14 -> 43927682 | G14: =+IFERROR(D14/C14-1,0) -> -1
A15: DEVOLUCION DE DSF - GASTOS BANCARIOS MES DE FEBRERO 2025 (DSF1104 AL 1114) | D15: -51359812 | F15: =+D15-C15 -> -51359812 | G15: =+IFERROR(D15/C15-1,0) -> 0
A16: FACTORING BBVA-29557-584-589-599-600-612-634-650 COMISION | D16: 12271970 | F16: =+D16-C16 -> 12271970 | G16: =+IFERROR(D16/C16-1,0) -> 0
A17: FACTORING BBVA FAN-29038 REGISTRO COMISION | C17: 1162707.3 | F17: =+D17-C17 -> -1162707.3 | G17: =+IFERROR(D17/C17-1,0) -> -1
A18: FACTORING BBVA FAN-29239 COMISIONES | C18: 1792877.1 | F18: =+D18-C18 -> -1792877.1 | G18: =+IFERROR(D18/C18-1,0) -> -1
A19: FACTORING BBVA FAN-29561 COMISION | D19: 1809003 | F19: =+D19-C19 -> 1809003 | G19: =+IFERROR(D19/C19-1,0) -> 0
A20: FACTORING BBVA FAN-29562-574-592-607-617-621-623-635-644-663-676 COMISIONES | D20: 14754923 | F20: =+D20-C20 -> 14754923 | G20: =+IFERROR(D20/C20-1,0) -> 0
A21: FACTORING BBVA-COMISIONES FAN-29218-251-256-288-309-324 | C21: 9251104.8 | F21: =+D21-C21 -> -9251104.8 | G21: =+IFERROR(D21/C21-1,0) -> -1
A22: GASTOS BANCARIOS CORRESPONDIENTES AL MES DE ENERO 2025 | C22: 43927682 | F22: =+D22-C22 -> -43927682 | G22: =+IFERROR(D22/C22-1,0) -> -1
A23: GASTOS BANCARIOS CORRESPONDIENTES AL MES DE FEBRERO 2025 | D23: 51359812 | F23: =+D23-C23 -> 51359812 | G23: =+IFERROR(D23/C23-1,0) -> 0
A24: RECLASIFICACION 529505 A 530515 COMISIONES BBVA - KLYM FEB 2025 | C24: 37562146 | F24: =+D24-C24 -> -37562146 | G24: =+IFERROR(D24/C24-1,0) -> -1
A25: RECLASIFICACION COMISIONES FACTORING BBVA NIC-36470 | D25: 16653282 | F25: =+D25-C25 -> 16653282 | G25: =+IFERROR(D25/C25-1,0) -> 0
A26: reclasificacion de cuentas en comision Factoring con Bavaria y Trululu | B26: 43927682 | F26: =+D26-C26 -> 0 | G26: =+IFERROR(D26/C26-1,0) -> 0
A27: RECLASIFICACION FAN-27800 A FAN - 27746 | C27: -639375 | F27: =+D27-C27 -> 639375 | G27: =+IFERROR(D27/C27-1,0) -> -1
A28: RECLASIFICION COMISIONES TRULULU FEB 2025 5295 A 5305 | C28: 2230352.2 | F28: =+D28-C28 -> -2230352.2 | G28: =+IFERROR(D28/C28-1,0) -> -1
A29: REGISTRO COMISION FACTORING BBVA | D29: 1069455.6 | F29: =+D29-C29 -> 1069455.6 | G29: =+IFERROR(D29/C29-1,0) -> 0
A30: COOPERATIVA COLANTA | D30: 1755101 | F30: =+D30-C30 -> 1755101 | G30: =+IFERROR(D30/C30-1,0) -> 0
A31: FACTORIN KLYM FAN-29555-29567-29582-29594 | D31: 1755101 | F31: =+D31-C31 -> 1755101 | G31: =+IFERROR(D31/C31-1,0) -> 0
A32: CORREAGRO S.A. | C32: 23022002 | D32: 19968668 | F32: =+D32-C32 -> -3053334 | G32: =+IFERROR(D32/C32-1,0) -> -0.13262678
A33: DAVIVIENDA | B33: 9801719 | C33: 8162148 | D33: 8069844 | F33: =+D33-C33 -> -92304 | G33: =+IFERROR(D33/C33-1,0) -> -0.011308788
A34: FIDUCIARIA DAVIVIENDA S.A | B34: 7426250 | C34: 3558750 | D34: 3558750.5 | F34: =+D34-C34 -> 0.5 | G34: =+IFERROR(D34/C34-1,0) -> 1.4049877e-07
A35: FIDUCIARIA POPULAR S.A. | B35: 3558750 | C35: 3558750 | D35: 4270500 | F35: =+D35-C35 -> 711750 | G35: =+IFERROR(D35/C35-1,0) -> 0.2
A36: ITAU CORPBANCA COLOMBIA SA | C36: 239997.6 | D36: 239997.6 | F36: =+D36-C36 -> 0 | G36: =+IFERROR(D36/C36-1,0) -> 0
A37: KLYM S.A.S | C37: 3496088 | F37: =+D37-C37 -> -3496088 | G37: =+IFERROR(D37/C37-1,0) -> -1
A38: SERVICIOS FINANCIEROS S.A. SERFINANZA CIA DE FINANCIAMIENTO | D38: 846982.5 | F38: =+D38-C38 -> 846982.5 | G38: =+IFERROR(D38/C38-1,0) -> 0
A39: Total general | B39: 74277097 | C39: 99598177 | D39: 1.4828035e+08
G40: =+GETPIVOTDATA("Neto",$A$3,"Mes",2)*G38 -> 0

Sheet TD 
A3: Suma de Neto | C3: Etiquetas de columna
A4: Etiquetas de fila | B4: Desc. auxiliar | C4: ENERO | D4: FEBRERO | E4: MARZO | F4: ABRIL | G4: MAYO | H4: 6 | I4: 7 | J4: 8 | K4: 9 | L4: 10
A5: 5502 - COMISIONES | C5: 74277097 | D5: 99598177 | E5: 1.1070745e+08 | F5: 1.1449795e+08 | G5: 1.2696958e+08 | H5: 99264624 | I5: 94136943 | J5: 55963595 | K5: 89318408 | L5: 1.7719002e+08
A6: 53051501 | B6: COMISIONES BANCARIAS | C6: 30349414 | D6: 21720275 | E6: 24705631 | F6: 20774654 | G6: 23685578 | H6: 19799540 | I6: 15160773 | J6: 11872594 | K6: 13893297 | L6: 10285606
B7: COMISIONES EN BOLSA | D7: 23022002 | E7: 19968668 | F7: -626070 | G7: 39499385 | H7: 15518647 | I7: 20002326 | J7: 23967947 | K7: 23705 | L7: 49513082
A8: 53051502 | B8: COMISIONES POR FACTORING | C8: 43927682 | D8: 54855900 | E8: 66033154 | F8: 94349366 | G8: 63784616 | H8: 63946437 | I8: 58973843 | J8: 20123054 | K8: 75401405 | L8: 1.1739133e+08
A9: Total general | C9: 74277097 | D9: 99598177 | E9: 1.1070745e+08 | F9: 1.1449795e+08 | G9: 1.2696958e+08 | H9: 99264624 | I9: 94136943 | J9: 55963595 | K9: 89318408 | L9: 1.7719002e+08

Sheet COMISIONES ENERO-MARZO 2025
A1: C.Costo | B1: Desc. C.Costo | C1: CUENTA | D1: Auxiliar | E1: Desc. auxiliar | F1: Neto | G1: Docto. | H1: Fecha | I1: Notas | J1: Notas docto | K1: Razón social tercero movto. | L1: SECCION | M1: Prefijo tipo docto | N1: SUB SUBCUENTA | O1: Mes
C2: 5502 - COMISIONES | D2: 53051501 | E2: BANCOS COMISIONES | F2: 38140 | G2: DSF-00001059 | H2: 45686 | I2: GASTOS BANCARIOS 27 AL 31 DICIEMBRE 2024 -BGTA CALI | J2: GASTOS BANCARIOS 27 AL 31 DICIEMBRE 2024 | K2: BANCO DE BOGOTA | M2: DSF | O2: =+MONTH(H2) -> 1
C3: 5502 - COMISIONES | D3: 53051501 | E3: BANCOS COMISIONES | F3: 78520 | G3: DSF-00001059 | H3: 45686 | I3: GASTOS BANCARIOS 27 AL 31 DICIEMBRE 2024 -BGTA TULUA | J3: GASTOS BANCARIOS 27 AL 31 DICIEMBRE 2024 | K3: BANCO DE BOGOTA | M3: DSF | O3: =+MONTH(H3) -> 1
C4: 5502 - COMISIONES | D4: 53051501 | E4: BANCOS COMISIONES | F4: 2500 | G4: DSF-00001060 | H4: 45686 | I4: GASTOS BANCARIOS 27 AL 31 DICIEMBRE 2024 -POPULAR 2276 | J4: GASTOS BANCARIOS 27 AL 31 DICIEMBRE 2024 -POPULAR 2276 | K4: BANCO POPULAR | M4: DSF | O4: =+MONTH(H4) -> 1
C5: 5502 - COMISIONES | D5: 53051501 | E5: BANCOS COMISIONES | F5: 125906.09 | G5: DSF-00001061 | H5: 45686 | I5: GASTOS BANCARIOS 27 AL 31 DICIEMBRE 2024 -BANCOLOMBIA 801 | J5: GASTOS BANCARIOS 27 AL 31 DICIEMBRE 2024 -BANCOLOMBIA | K5: BANCOLOMBIA | M5: DSF | O5: =+MONTH(H5) -> 1
C6: 5502 - COMISIONES | D6: 53051501 | E6: BANCOS COMISIONES | F6: 16560 | G6: DSF-00001061 | H6: 45686 | I6: GASTOS BANCARIOS 27 AL 31 DICIEMBRE 2024 -BANCOLOMBIA ESPECIAL | J6: GASTOS BANCARIOS 27 AL 31 DICIEMBRE 2024 -BANCOLOMBIA | K6: BANCOLOMBIA | M6: DSF | O6: =+MONTH(H6) -> 1
C7: 5502 - COMISIONES | D7: 53051501 | E7: BANCOS COMISIONES | F7: 4303049 | G7: DSF-00001074 | H7: 45707 | I7: GASTOS BANCARIOS CORRESPONDIENTES AL MES DE ENERO 2025 | J7: GASTOS BANCARIOS CORRESPONDIENTES AL MES DE ENERO 2025 | K7: BANCO DE BOGOTA | M7: DSF | O7: =+MONTH(H7) -> 2
C8: 5502 - COMISIONES | D8: 53051501 | E8: BANCOS COMISIONES | F8: 4739977 | G8: DSF-00001076 | H8: 45707 | I8: GASTOS BANCARIOS CORRESPONDIENTES AL MES DE ENERO 2025 | J8: GASTOS BANCARIOS CORRESPONDIENTES AL MES DE ENERO 2025 | K8: BANCOLOMBIA | M8: DSF | O8: =+MONTH(H8) -> 2
C9: 5502 - COMISIONES | D9: 53051501 | E9: BANCOS COMISIONES | F9: 9801719 | G9: DSF-00001077 | H9: 45707 | I9: GASTOS BANCARIOS CORRESPONDIENTES AL MES DE ENERO 2025 | J9: GASTOS BANCARIOS CORRESPONDIENTES AL MES DE ENERO 2025 | K9: DAVIVIENDA | M9: DSF | O9: =+MONTH(H9) -> 2
C10: 5502 - COMISIONES | D10: 53051501 | E10: BANCOS COMISIONES | F10: 2190 | G10: DSF-00001078 | H10: 45707 | I10: GASTOS BANCARIOS CORRESPONDIENTES AL MES DE ENERO 2025 | J10: GASTOS BANCARIOS CORRESPONDIENTES AL MES DE ENERO 2025 | K10: BANCO AGRARIO DE COLOMBIA S.A | M10: DSF | O10: =+MONTH(H10) -> 2
C11: 5502 - COMISIONES | D11: 53051501 | E11: BANCOS COMISIONES | F11: 2650 | G11: DSF-00001079 | H11: 45707 | I11: GASTOS BANCARIOS CORRESPONDIENTES AL MES DE ENERO 2025 | J11: GASTOS BANCARIOS CORRESPONDIENTES AL MES DE ENERO 2025 | K11: BANCO POPULAR | M11: DSF | O11: =+MONTH(H11) -> 2
C12: 5502 - COMISIONES | D12: 53051501 | E12: BANCOS COMISIONES | F12: 43927682 | G12: DSF-00001081 | H12: 45707 | I12: GASTOS BANCARIOS CORRESPONDIENTES AL MES DE ENERO 2025 | J12: GASTOS BANCARIOS CORRESPONDIENTES AL MES DE ENERO 2025 | K12: BBVA COLOMBIA S.A. | M12: DSF | O12: =+MONTH(H12) -> 2
C13: 5502 - COMISIONES | D13: 53051501 | E13: BANCOS COMISIONES | F13: 3558750 | G13: DSF-00001082 | H13: 45707 | I13: GASTOS BANCARIOS CORRESPONDIENTES AL MES DE ENERO 2025 | J13: GASTOS BANCARIOS CORRESPONDIENTES AL MES DE ENERO 2025 | K13: FIDUCIARIA POPULAR S.A. | M13: DSF | O13: =+MONTH(H13) -> 2
... C23: 5502 - COMISIONES | D23: 53051501 | E23: BANCOS COMISIONES | F23: 284369.99 | G23: DSF-00001114 | H23: 45737 | I23: GASTOS BANCARIOS CORRESPONDIENTES AL MES DE FEBRERO 2025 | J23: GASTOS BANCARIOS CORRESPONDIENTES AL MES DE FEBRERO 2025 | K23: BANCOLOMBIA PANAMA | M23: DSF | O23: =+MONTH(H23) -> 3
C24: 5502 - COMISIONES | D24: 53051501 | E24: BANCOS COMISIONES | F24: 3558750 | G24: FAC-00045087 | H24: 45688 | I24: FAC132801 - COMISION FIDUCIARIA MES DE ENERO 2025- COMISION FIJA 2.5 SMMLV | J24: FAC132801 - COMISION FIDUCIARIA MES DE ENERO 2025- COMISION FIJA 2.5 SMMLV | K24: FIDUCIARIA POPULAR S.A. | O24: =+MONTH(H24) -> 1
C25: 5502 - COMISIONES | D25: 53051501 | E25: BANCOS COMISIONES | F25: 3558750 | G25: FAC-00045088 | H25: 45688 | I25: SOC81109 - COMISION POR ADMINISTRACION MES DE ENERO 2025 - EA | J25: SOC81109 - COMISION POR ADMINISTRACION MES DE ENERO 2025 - EA | K25: FIDUCIARIA DAVIVIENDA S.A | O25: =+MONTH(H25) -> 1
C26: 5502 - COMISIONES | D26: 53051501 | E26: BANCOS COMISIONES | F26: 3558750 | G26: FAC-00045545 | H26: 45716 | I26: SOC82093 - D1- COMISION POR ADMINISTRACION, PERIODO DE FACTRUACION: FEBRERO 2025 | J26: SOC82093 - D1- COMISION POR ADMINISTRACION, PERIODO DE FACTRUACION: FEBRERO 2025 | K26: FIDUCIARIA DAVIVIENDA S.A | O26: =+MONTH(H26) -> 2
C27: 5502 - COMISIONES | D27: 53051501 | E27: BANCOS COMISIONES | F27: 3558750 | G27: FAC-00045546 | H27: 45716 | I27: FAC133255 - COMISION FIDUCIARIA MES DE FEBRERO 2025- COMISION FIJA 2.5 SMMLV | J27: FAC133255 - COMISION FIDUCIARIA MES DE FEBRERO 2025- COMISION FIJA 2.5 SMMLV | K27: FIDUCIARIA POPULAR S.A. | O27: =+MONTH(H27) -> 2
C28: 5502 - COMISIONES | D28: 53051501 | E28: BANCOS COMISIONES | F28: 711750 | G28: FAC-00045697 | H28: 45733 | I28: FAC133431 - COMISION FIDUCIARIA POR EXPEDICION DE CERTIFICADO DE GARANTIA 20 | J28: FAC133431 - COMISION FIDUCIARIA POR EXPEDICION DE CERTIFICADO DE GARANTIA 20 | K28: FIDUCIARIA POPULAR S.A. | O28: =+MONTH(H28) -> 3
C29: 5502 - COMISIONES | D29: 53051501 | E29: BANCOS COMISIONES | F29: 3558750 | G29: FAC-00045698 | H29: 45733 | I29: FAC133535 - COMISION FIDUCIARIA MES DE MARZO 2025 - COMISION FIJA 2.5 SMMLV | J29: FAC133535 - COMISION FIDUCIARIA MES DE MARZO 2025 - COMISION FIJA 2.5 SMMLV | K29: FIDUCIARIA POPULAR S.A. | O29: =+MONTH(H29) -> 3
C30: 5502 - COMISIONES | D30: 53051501 | E30: BANCOS COMISIONES | F30: 3558750 | G30: FAC-00045701 | H30: 45733 | I30: SOC83617 - COMISION POR ADMINISTRACION - PERIODO DE FACTURACION MARZO 2025 | J30: SOC83617 - COMISION POR ADMINISTRACION - PERIODO DE FACTURACION MARZO 2025 | K30: FIDUCIARIA DAVIVIENDA S.A | O30: =+MONTH(H30) -> 3
C31: 5502 - COMISIONES | D31: 53051501 | E31: BANCOS COMISIONES | F31: 1423500 | G31: FAC-00045724 | H31: 45736 | I31: FAC992663 - COMISION FIJA DE ADMINISTRACION CORRESPONDIENTE AL MES DE MARZO 2025 | J31: FAC992663 - COMISION FIJA DE ADMINISTRACION CORRESPONDIENTE AL MES DE MARZO 2025 | K31: ALIANZA FIDUCIARIA S.A | O31: =+MONTH(H31) -> 3
C32: 5502 - COMISIONES | D32: 53051501 | E32: BANCOS COMISIONES | F32: 2190 | G32: NIB-00005736 | H32: 45664 | I32: PAGO DE DEPOSITOS JUDICIALES - COMPROBANTE DE PAGO: 1491465 - ARCHIVO: 30030 - INGENIO CARMELITA - ARCHIVO: GD20250107018919001961 | J32: PAGO DE DEPOSITOS JUDICIALES - COMPROBANTE DE PAGO: 1491465 - ARCHIVO: 30030 - INGENIO CARMELITA - ARCHIVO: GD20250107018919001961 | K32: BANCO AGRARIO DE COLOMBIA | O32: =+MONTH(H32) -> 1
C33: 5502 - COMISIONES | D33: 53051501 | E33: BANCOS COMISIONES | F33: 9600.49 | G33: NIB-00005875 | H33: 45688 | I33: COSTO DE TRANSACCION -PAGO DE FACTURAS A NOMBRE DE INGENIERIA Y EQUIPOS PARA LA INGENIERIA | J33: PAGO DE FACTURAS A NOMBRE DE INGENIERIA Y EQUIPOS PARA LA INGENIERIA | K33: BANCOLOMBIA | O33: =+MONTH(H33) -> 1
C34: 5502 - COMISIONES | D34: 53051501 | E34: BANCOS COMISIONES | F34: 1824 | G34: NIB-00005875 | H34: 45688 | I34: IVA DE TRANSACCION -PAGO DE FACTURAS A NOMBRE DE INGENIERIA Y EQUIPOS PARA LA INGENIERIA | J34: PAGO DE FACTURAS A NOMBRE DE INGENIERIA Y EQUIPOS PARA LA INGENIERIA | K34: BANCOLOMBIA | O34: =+MONTH(H34) -> 1
C35: 5502 - COMISIONES | D35: 53051501 | E35: BANCOS COMISIONES | F35: 3867500 | G35: NIB-00005899 | H35: 45688 | I35: COMISION FIJA MES DE ENERO 2025 | J35: GASTOS BANCARIOS MES DE ENERO 2025 FIDEICOMISO 42112858 - RENTA LIQUIDAN GASTOS BANCARIOS MES DE ENERO 2025 FIDEICOMISO 42112858 - RENTA LIQUIDA | K35: FIDUCIARIA DAVIVIENDA S.A | O35: =+MONTH(H35) -> 1
... C127: 5502 - COMISIONES | D127: 53051501 | E127: BANCOS COMISIONES | F127: 4782185 | G127: NIP-00016935 | H127: 45747 | I127: CLFV21376 - SERV REGISTRADO BMC 8600071250 | J127: CLFV21376 - SERV REGISTRADO BMC 8600071250 | K127: CORREAGRO S.A. | O127: =+MONTH(H127) -> 3
A128: Gran total | F128: 3.2215562e+08 | O128: =+MONTH(H128) -> 1

Sheet COMISIONES ENERO-MARZO 2025 (2)
A1: C.Costo | B1: Desc. C.Costo | C1: CUENTA | D1: Auxiliar | E1: Desc. auxiliar | F1: Neto | G1: Docto. | H1: Fecha | I1: Notas | J1: Notas docto | K1: Razón social tercero movto. | L1: SECCION | M1: Prefijo tipo docto | N1: SUB SUBCUENTA | O1: Mes | P1: Nombre Mes | X1: 1 | Y1: Enero
C2: 5502 - COMISIONES | D2: 53051501 | E2: COMISIONES BANCARIAS | F2: 2190 | G2: NIB-00005736 | H2: 45664 | I2: PAGO DE DEPOSITOS JUDICIALES - COMPROBANTE DE PAGO: 1491465 - ARCHIVO: 30030 - INGENIO CARMELITA - ARCHIVO: GD20250107018919001961 | J2: PAGO DE DEPOSITOS JUDICIALES - COMPROBANTE DE PAGO: 1491465 - ARCHIVO: 30030 - INGENIO CARMELITA - ARCHIVO: GD20250107018919001961 | K2: BANCO AGRARIO DE COLOMBIA S.A | M2: DSF | O2: =+MONTH(H2) -> 1 | P2: =+VLOOKUP(O2,$X:$Y,2,0) -> Enero | X2: 2 | Y2: Febrero
C3: 5502 - COMISIONES | D3: 53051501 | E3: COMISIONES BANCARIAS | F3: 3529 | G3: NIP-00016497 | H3: 45665 | I3: CONTABILIZACIÓN IVA COMISON 4*1000 | J3: CONTABILIZACIÓN IVA COMISON 4*1000 | K3: BANCOLOMBIA | M3: DSF | O3: =+MONTH(H3) -> 1 | P3: =+VLOOKUP(O3,X:Y,2,0) -> Enero | X3: 3 | Y3: Marzo
C4: 5502 - COMISIONES | D4: 53051501 | E4: COMISIONES BANCARIAS | F4: 7058 | G4: NIP-00016498 | H4: 45665 | I4: CONTABILIZACIÓN IVA COMISON 4*1000 | J4: CONTABILIZACIÓN IVA COMISON 4*1000 | K4: BANCOLOMBIA | M4: DSF | O4: =+MONTH(H4) -> 1 | P4: =+VLOOKUP(O4,X:Y,2,0) -> Enero | X4: 4 | Y4: Abril
C5: 5502 - COMISIONES | D5: 53051501 | E5: COMISIONES BANCARIAS | F5: 3529 | G5: NIP-00016519 | H5: 45671 | I5: CONTABILIZACIÓN IVA COMISION 4*1000 | J5: CONTABILIZACIÓN IVA COMISION 4*1000 | K5: BANCOLOMBIA | M5: DSF | O5: =+MONTH(H5) -> 1 | P5: =+VLOOKUP(O5,X:Y,2,0) -> Enero | X5: 5 | Y5: Mayo
C6: 5502 - COMISIONES | D6: 53051501 | E6: COMISIONES BANCARIAS | F6: 2650 | G6: NIB-00005915 | H6: 45674 | I6: GASTOS BANCARIOS POPULAR 2276 MES DE ENERO 2025 | J6: GASTOS BANCARIOS POPULAR 2276 MES DE ENERO 2025 | K6: BANCO POPULAR | M6: DSF | O6: =+MONTH(H6) -> 1 | P6: =+VLOOKUP(O6,X:Y,2,0) -> Enero | X6: 6 | Y6: Junio
C7: 5502 - COMISIONES | D7: 53051501 | E7: COMISIONES BANCARIAS | F7: 3529 | G7: NIP-00016556 | H7: 45678 | I7: CONTAN¿BILIZACIÓN IVA 4*1000 COMISION | J7: CONTAN¿BILIZACIÓN IVA 4*1000 COMISION | K7: BANCOLOMBIA | M7: DSF | O7: =+MONTH(H7) -> 1 | P7: =+VLOOKUP(O7,X:Y,2,0) -> Enero | X7: 7 | Y7: Julio
C8: 5502 - COMISIONES | D8: 53051501 | E8: COMISIONES BANCARIAS | F8: 3529 | G8: NIP-00016562 | H8: 45679 | I8: contabilización iva comision 4*1000 | J8: contabilización iva comision 4*1000 | K8: BANCOLOMBIA | M8: DSF | O8: =+MONTH(H8) -> 1 | P8: =+VLOOKUP(O8,X:Y,2,0) -> Enero | X8: 8 | Y8: Agosto
C9: 5502 - COMISIONES | D9: 53051501 | E9: COMISIONES BANCARIAS | F9: 3529 | G9: NIP-00016588 | H9: 45684 | I9: CONTABILIZACIÓN IVA COMISION 4*1000 | J9: CONTABILIZACIÓN IVA COMISION 4*1000 | K9: BANCOLOMBIA | M9: DSF | O9: =+MONTH(H9) -> 1 | P9: =+VLOOKUP(O9,X:Y,2,0) -> Enero | X9: 9 | Y9: Septiembre
C10: 5502 - COMISIONES | D10: 53051501 | E10: COMISIONES BANCARIAS | F10: 38140 | G10: DSF-00001059 | H10: 45686 | I10: GASTOS BANCARIOS 27 AL 31 DICIEMBRE 2024 -BGTA CALI | J10: GASTOS BANCARIOS 27 AL 31 DICIEMBRE 2024 | K10: BANCO DE BOGOTA | M10: DSF | O10: =+MONTH(H10) -> 1 | P10: =+VLOOKUP(O10,X:Y,2,0) -> Enero | X10: 10 | Y10: Octubre
C11: 5502 - COMISIONES | D11: 53051501 | E11: COMISIONES BANCARIAS | F11: 78520 | G11: DSF-00001059 | H11: 45686 | I11: GASTOS BANCARIOS 27 AL 31 DICIEMBRE 2024 -BGTA TULUA | J11: GASTOS BANCARIOS 27 AL 31 DICIEMBRE 2024 | K11: BANCO DE BOGOTA | M11: DSF | O11: =+MONTH(H11) -> 1 | P11: =+VLOOKUP(O11,X:Y,2,0) -> Enero | X11: 11 | Y11: Noviembre
C12: 5502 - COMISIONES | D12: 53051501 | E12: COMISIONES BANCARIAS | F12: 2500 | G12: DSF-00001060 | H12: 45686 | I12: GASTOS BANCARIOS 27 AL 31 DICIEMBRE 2024 -POPULAR 2276 | J12: GASTOS BANCARIOS 27 AL 31 DICIEMBRE 2024 -POPULAR 2276 | K12: BANCO POPULAR | M12: DSF | O12: =+MONTH(H12) -> 1 | P12: =+VLOOKUP(O12,X:Y,2,0) -> Enero | X12: 12 | Y12: Diciembre
C13: 5502 - COMISIONES | D13: 53051501 | E13: COMISIONES BANCARIAS | F13: 125906.09 | G13: DSF-00001061 | H13: 45686 | I13: GASTOS BANCARIOS 27 AL 31 DICIEMBRE 2024 -BANCOLOMBIA 801 | J13: GASTOS BANCARIOS 27 AL 31 DICIEMBRE 2024 -BANCOLOMBIA | K13: BANCOLOMBIA | M13: DSF | O13: =+MONTH(H13) -> 1 | P13: =+VLOOKUP(O13,X:Y,2,0) -> Enero
C14: 5502 - COMISIONES | D14: 53051501 | E14: COMISIONES BANCARIAS | F14: 16560 | G14: DSF-00001061 | H14: 45686 | I14: GASTOS BANCARIOS 27 AL 31 DICIEMBRE 2024 -BANCOLOMBIA ESPECIAL | J14: GASTOS BANCARIOS 27 AL 31 DICIEMBRE 2024 -BANCOLOMBIA | K14: BANCOLOMBIA | M14: DSF | O14: =+MONTH(H14) -> 1 | P14: =+VLOOKUP(O14,X:Y,2,0) -> Enero
C15: 5502 - COMISIONES | D15: 53051501 | E15: COMISIONES BANCARIAS | F15: -125906.09 | G15: NIC-00035976 | H15: 45686 | I15: GASTOS BANCARIOS 27 AL 31 DICIEMBRE 2024 -BANCOLOMBIA 801 | J15: DEVOLUCION DE DSF 1059-1060-1061 - GASTOS BANCARIOS 27 AL 31 DIC 2024 | K15: BANCOLOMBIA | M15: DSF | O15: =+MONTH(H15) -> 1 | P15: =+VLOOKUP(O15,X:Y,2,0) -> Enero
C16: 5502 - COMISIONES | D16: 53051501 | E16: COMISIONES BANCARIAS | F16: -16560 | G16: NIC-00035976 | H16: 45686 | I16: GASTOS BANCARIOS 27 AL 31 DICIEMBRE 2024 -BANCOLOMBIA ESPECIAL | J16: DEVOLUCION DE DSF 1059-1060-1061 - GASTOS BANCARIOS 27 AL 31 DIC 2024 | K16: BANCOLOMBIA | M16: DSF | O16: =+MONTH(H16) -> 1 | P16: =+VLOOKUP(O16,X:Y,2,0) -> Enero
C17: 5502 - COMISIONES | D17: 53051501 | E17: COMISIONES BANCARIAS | F17: -38140 | G17: NIC-00035976 | H17: 45686 | I17: GASTOS BANCARIOS 27 AL 31 DICIEMBRE 2024 -BGTA CALI | J17: DEVOLUCION DE DSF 1059-1060-1061 - GASTOS BANCARIOS 27 AL 31 DIC 2024 | K17: BANCO DE BOGOTA | M17: DSF | O17: =+MONTH(H17) -> 1 | P17: =+VLOOKUP(O17,X:Y,2,0) -> Enero
C18: 5502 - COMISIONES | D18: 53051501 | E18: COMISIONES BANCARIAS | F18: -78520 | G18: NIC-00035976 | H18: 45686 | I18: GASTOS BANCARIOS 27 AL 31 DICIEMBRE 2024 -BGTA TULUA | J18: DEVOLUCION DE DSF 1059-1060-1061 - GASTOS BANCARIOS 27 AL 31 DIC 2024 | K18: BANCO DE BOGOTA | M18: DSF | O18: =+MONTH(H18) -> 1 | P18: =+VLOOKUP(O18,X:Y,2,0) -> Enero
C19: 5502 - COMISIONES | D19: 53051501 | E19: COMISIONES BANCARIAS | F19: -2500 | G19: NIC-00035976 | H19: 45686 | I19: GASTOS BANCARIOS 27 AL 31 DICIEMBRE 2024 -POPULAR 2276 | J19: DEVOLUCION DE DSF 1059-1060-1061 - GASTOS BANCARIOS 27 AL 31 DIC 2024 | K19: BANCO POPULAR | M19: DSF | O19: =+MONTH(H19) -> 1 | P19: =+VLOOKUP(O19,X:Y,2,0) -> Enero
C20: 5502 - COMISIONES | D20: 53051501 | E20: COMISIONES BANCARIAS | F20: 3529 | G20: NIP-00016610 | H20: 45686 | I20: contabilización de iva comision 4*1000 | J20: contabilización de iva comision 4*1000 | K20: BANCOLOMBIA | M20: DSF | O20: =+MONTH(H20) -> 1 | P20: =+VLOOKUP(O20,X:Y,2,0) -> Enero
C21: 5502 - COMISIONES | D21: 53051501 | E21: COMISIONES BANCARIAS | F21: 3558750 | G21: FAC-00045087 | H21: 45688 | I21: FAC132801 - COMISION FIDUCIARIA MES DE ENERO 2025- COMISION FIJA 2.5 SMMLV | J21: FAC132801 - COMISION FIDUCIARIA MES DE ENERO 2025- COMISION FIJA 2.5 SMMLV | K21: FIDUCIARIA POPULAR S.A. | M21: DSF | O21: =+MONTH(H21) -> 1 | P21: =+VLOOKUP(O21,X:Y,2,0) -> Enero
C22: 5502 - COMISIONES | D22: 53051501 | E22: COMISIONES BANCARIAS | F22: 3558750 | G22: FAC-00045088 | H22: 45688 | I22: SOC81109 - COMISION POR ADMINISTRACION MES DE ENERO 2025 - EA | J22: SOC81109 - COMISION POR ADMINISTRACION MES DE ENERO 2025 - EA | K22: FIDUCIARIA DAVIVIENDA S.A | M22: DSF | O22: =+MONTH(H22) -> 1 | P22: =+VLOOKUP(O22,X:Y,2,0) -> Enero
C23: 5502 - COMISIONES | D23: 53051501 | E23: COMISIONES BANCARIAS | F23: 9600.49 | G23: NIB-00005875 | H23: 45688 | I23: COSTO DE TRANSACCION -PAGO DE FACTURAS A NOMBRE DE INGENIERIA Y EQUIPOS PARA LA INGENIERIA | J23: PAGO DE FACTURAS A NOMBRE DE INGENIERIA Y EQUIPOS PARA LA INGENIERIA | K23: BANCOLOMBIA | M23: DSF | O23: =+MONTH(H23) -> 1 | P23: =+VLOOKUP(O23,X:Y,2,0) -> Enero
C24: 5502 - COMISIONES | D24: 53051501 | E24: COMISIONES BANCARIAS | F24: 1824 | G24: NIB-00005875 | H24: 45688 | I24: IVA DE TRANSACCION -PAGO DE FACTURAS A NOMBRE DE INGENIERIA Y EQUIPOS PARA LA INGENIERIA | J24: PAGO DE FACTURAS A NOMBRE DE INGENIERIA Y EQUIPOS PARA LA INGENIERIA | K24: BANCOLOMBIA | O24: =+MONTH(H24) -> 1 | P24: =+VLOOKUP(O24,X:Y,2,0) -> Enero
C25: 5502 - COMISIONES | D25: 53051501 | E25: COMISIONES BANCARIAS | F25: 3867500 | G25: NIB-00005899 | H25: 45688 | I25: COMISION FIJA MES DE ENERO 2025 | J25: GASTOS BANCARIOS MES DE ENERO 2025 FIDEICOMISO 42112858 - RENTA LIQUIDAN GASTOS BANCARIOS MES DE ENERO 2025 FIDEICOMISO 42112858 - RENTA LIQUIDA | K25: FIDUCIARIA DAVIVIENDA S.A | O25: =+MONTH(H25) -> 1 | P25: =+VLOOKUP(O25,X:Y,2,0) -> Enero
C26: 5502 - COMISIONES | D26: 53051501 | E26: COMISIONES BANCARIAS | F26: 514829.43 | G26: NIB-00005902 | H26: 45688 | I26: GASTOS BANCARIOS MES DE ENERO 2025- BANCOLOMBIA PANAMA | J26: GASTOS BANCARIOS MES DE ENERO 2025- BANCOLOMBIA PANAMA | K26: BANCOLOMBIA PANAMA | O26: =+MONTH(H26) -> 1 | P26: =+VLOOKUP(O26,X:Y,2,0) -> Enero
C27: 5502 - COMISIONES | D27: 53051501 | E27: COMISIONES BANCARIAS | F27: 4280613 | G27: NIB-00005906 | H27: 45688 | I27: GASTOS BANCARIOS BOGOTA TULUA 612036319- MES DE ENERO 2025 | J27: GASTOS BANCARIOS BOGOTA TULUA 612036319- MES DE ENERO 2025 | K27: BANCO DE BOGOTA | O27: =+MONTH(H27) -> 1 | P27: =+VLOOKUP(O27,X:Y,2,0) -> Enero
C28: 5502 - COMISIONES | D28: 53051501 | E28: COMISIONES BANCARIAS | F28: 4700320.5 | G28: NIB-00005911 | H28: 45688 | I28: GASTOS BANCARIOS BANCOLOMBIA CTA CTE 80104152201 - MES DE ENERO 2025 | J28: GASTOS BANCARIOS BANCOLOMBIA CTA CTE 80104152201 - MES DE ENERO 2025 | K28: BANCOLOMBIA | O28: =+MONTH(H28) -> 1 | P28: =+VLOOKUP(O28,X:Y,2,0) -> Enero
C29: 5502 - COMISIONES | D29: 53051501 | E29: COMISIONES BANCARIAS | F29: 9801719 | G29: NIB-00005919 | H29: 45688 | I29: GASTOS BANCARIOS DAVIVIENDA 7678 MES DE ENERO 2025 | J29: GASTOS BANCARIOS DAVIVIENDA 7678 MES DE ENERO 2025 | K29: BANCO DAVIVIENDA S.A | O29: =+MONTH(H29) -> 1 | P29: =+VLOOKUP(O29,X:Y,2,0) -> Enero
C30: 5502 - COMISIONES | D30: 53051501 | E30: COMISIONES BANCARIAS | F30: 22436 | G30: NIB-00005936 | H30: 45688 | I30: GASTOS BANCARIOS BGTA CALI 256096355 MES DE ENERO 2025 | J30: GASTOS BANCARIOS BGTA CALI 256096355 MES DE ENERO 2025 | K30: BANCO DE BOGOTA | O30: =+MONTH(H30) -> 1 | P30: =+VLOOKUP(O30,X:Y,2,0) -> Enero
C31: 5502 - COMISIONES | D31: 53051502 | E31: COMISIONES POR FACTORING | F31: 7087724.8 | G31: NIC-00036152 | H31: 45688 | I31: COMISIONES FACTORIGN TRULULU FAN-28253-255 SUPER ALIMENTOS 28207-225-261-262 | J31: reclasificacion de cuentas en comision Factoring con Bavaria y Trululu | K31: BBVA COLOMBIA S.A. | O31: =+MONTH(H31) -> 1 | P31: =+VLOOKUP(O31,X:Y,2,0) -> Enero
C32: 5502 - COMISIONES | D32: 53051502 | E32: COMISIONES POR FACTORING | F32: 36839957 | G32: NIC-00036152 | H32: 45688 | I32: REGISTRO COMISION FACTORING BBVA FAN-27806-848-849-850-862-863-864 | J32: reclasificacion de cuentas en comision Factoring con Bavaria y Trululu | K32: BBVA COLOMBIA S.A. | O32: =+MONTH(H32) -> 1 | P32: =+VLOOKUP(O32,X:Y,2,0) -> Enero
C33: 5502 - COMISIONES | D33: 53051501 | E33: COMISIONES BANCARIAS | F33: 3529 | G33: NIC-00036050 | H33: 45692 | I33: CONTABILIZACIÓN IVA COMISION 4*1000 | J33: CONTABILIZACIÓN IVA COMISION 4*1000 | K33: BANCOLOMBIA | O33: =+MONTH(H33) -> 2 | P33: =+VLOOKUP(O33,X:Y,2,0) -> Febrero
C34: 5502 - COMISIONES | D34: 53051501 | E34: COMISIONES BANCARIAS | F34: 3529 | G34: NIC-00036051 | H34: 45692 | I34: CONTABILIZACIÓN IVA COMISION 4*1000 | J34: CONTABILIZACIÓN IVA COMISON 4*1000 | K34: BANCOLOMBIA | O34: =+MONTH(H34) -> 2 | P34: =+VLOOKUP(O34,X:Y,2,0) -> Febrero
C35: 5502 - COMISIONES | D35: 53051501 | E35: COMISIONES BANCARIAS | F35: 3529 | G35: NIC-00036053 | H35: 45692 | I35: CONTABILIZACIÓN IVA COMISION 4*1000 | J35: CONTABILIZACION IVA COMISON 4*1000 | K35: BANCOLOMBIA | O35: =+MONTH(H35) -> 2 | P35: =+VLOOKUP(O35,X:Y,2,0) -> Febrero
... C132: 5502 - COMISIONES | D132: 53051501 | E132: COMISIONES EN BOLSA | F132: 4782185 | G132: NIP-00016935 | H132: 45747 | I132: CLFV21376 - SERV REGISTRADO BMC 8600071250 | J132: CLFV21376 - SERV REGISTRADO BMC 8600071250 | K132: CORREAGRO S.A. | O132: =+MONTH(H132) -> 3 | P132: =+VLOOKUP(O132,X:Y,2,0) -> Marzo
C133: 5502 - COMISIONES | D133: 53051501 | E133: COMISIONES BANCARIAS | F133: 3529 | G133: NIP-00016938 | H133: 45749 | I133: CONTABILIZACIÓN IVA COMISION 4*1000 | J133: CONTABILIZACIÓN IVA COMISION 4*1000 | K133: BANCOLOMBIA | M133: DSF | O133: =+MONTH(H133) -> 4 | P133: =+VLOOKUP(O133,X:Y,2,0) -> Abril
C134: 5502 - COMISIONES | D134: 53051501 | E134: COMISIONES BANCARIAS | F134: 3529 | G134: NIP-00016939 | H134: 45749 | I134: CONTABILIZACIÓN IVA COMISION 4*1000 | J134: CONTABILIZACIÓN IVA COMISION 4*1000 | K134: BANCOLOMBIA | M134: DSF | O134: =+MONTH(H134) -> 4 | P134: =+VLOOKUP(O134,X:Y,2,0) -> Abril
C135: 5502 - COMISIONES | D135: 53051501 | E135: COMISIONES BANCARIAS | F135: 3529 | G135: NIP-00016940 | H135: 45749 | I135: CONTABILIZACIÓN IVA COMISION 4*1000 | J135: CONTABILIZACIÓN IVA COMISION 4*1000 | K135: BANCOLOMBIA | M135: DSF | O135: =+MONTH(H135) -> 4 | P135: =+VLOOKUP(O135,X:Y,2,0) -> Abril
C136: 5502 - COMISIONES | D136: 53051501 | E136: COMISIONES BANCARIAS | F136: 13140 | G136: NIB-00006418 | H136: 45754 | I136: PAGO DE DEPOSITOS JUDICIALES ICSA - SECUENCIAL ARCHIVO: 1513049 - GD2025040708891900196 - 30030 | J136: PAGO DE DEPOSITOS JUDICIALES ICSA - SECUENCIAL ARCHIVO: 1513049 - GD2025040708891900196 - 30030 | K136: BANCO AGRARIO DE COLOMBIA S.A | M136: DSF | O136: =+MONTH(H136) -> 4 | P136: =+VLOOKUP(O136,X:Y,2,0) -> Abril
C137: 5502 - COMISIONES | D137: 53051502 | E137: COMISIONES POR FACTORING | F137: 23550216 | G137: NIB-00006420 | H137: 45755 | I137: REGISTRO COMISION FACTOING BBVA FAN 29557-29561-29584-29589-29599-29600-29612-29634-29650-29656-29667-29674-29695-29719-29734 | J137: REGISTRO COMISION FACTOING BBVA FAN 29557-29561-29584-29589-29599-29600-29612-29634-29650-29656-29667-29674-29695-29719-29734 | K137: BBVA COLOMBIA S.A. | M137: DSF | O137: =+MONTH(H137) -> 4 | P137: =+VLOOKUP(O137,X:Y,2,0) -> Abril
C138: 5502 - COMISIONES | D138: 53051502 | E138: COMISIONES POR FACTORING | F138: 629958.5 | G138: NIB-00006577 | H138: 45755 | I138: FACTORING KLYM - COMISIONES FAN-29726 | J138: FACTORING KLYM - COMISIONES FAN-29726 | K138: KLYM S.A.S | M138: DSF | O138: =+MONTH(H138) -> 4 | P138: =+VLOOKUP(O138,X:Y,2,0) -> Abril
C139: 5502 - COMISIONES | D139: 53051501 | E139: COMISIONES BANCARIAS | F139: 3529 | G139: NIP-00016959 | H139: 45756 | I139: CONTABILIZACIÓN IVA COMISION 4*1000 | J139: CONTABILIZACIÓN IVA COMISION 4*1000 | K139: BANCOLOMBIA | M139: DSF | O139: =+MONTH(H139) -> 4 | P139: =+VLOOKUP(O139,X:Y,2,0) -> Abril
C140: 5502 - COMISIONES | D140: 53051502 | E140: COMISIONES POR FACTORING | F140: 10931486 | G140: NIC-00037061 | H140: 45757 | I140: COMISION FACTORING BBVA | J140: COMISION FACTORING BBVA | K140: BBVA COLOMBIA S.A. | M140: DSF | O140: =+MONTH(H140) -> 4 | P140: =+VLOOKUP(O140,X:Y,2,0) -> Abril
C141: 5502 - COMISIONES | D141: 53051502 | E141: COMISIONES POR FACTORING | F141: 26254604 | G141: NIC-00037064 | H141: 45757 | I141: REGISTRO COMISION FACTORING BBVA ABRIL | J141: REGISTRO COMISION FACTORING BBVA | K141: BBVA COLOMBIA S.A. | M141: DSF | O141: =+MONTH(H141) -> 4 | P141: =+VLOOKUP(O141,X:Y,2,0) -> Abril
C142: 5502 - COMISIONES | D142: 53051501 | E142: COMISIONES EN BOLSA | F142: -271584 | G142: NCS-00000127 | H142: 45761 | I142: CRUCE DE NOTA CREDITO ENCL139 - DE LAS FACTURA FZ21377 | J142: CRUCE DE NOTA CREDITO ENCL139 - DE LAS FACTURA FZ21377 | K142: CORREAGRO S.A. | M142: DSF | O142: =+MONTH(H142) -> 4 | P142: =+VLOOKUP(O142,X:Y,2,0) -> Abril
C143: 5502 - COMISIONES | D143: 53051501 | E143: COMISIONES EN BOLSA | F143: -87576 | G143: NCS-00000128 | H143: 45761 | I143: CRUCE DE NOTA CREDITO ENCL138 - DE LAS FACTURA CLFV21376 | J143: CRUCE DE NOTA CREDITO ENCL138 - DE LAS FACTURA CLFV21376 | K143: CORREAGRO S.A. | M143: DSF | O143: =+MONTH(H143) -> 4 | P143: =+VLOOKUP(O143,X:Y,2,0) -> Abril
C144: 5502 - COMISIONES | D144: 53051501 | E144: COMISIONES EN BOLSA | F144: -266910 | G144: NCS-00000129 | H144: 45761 | I144: CRUCE DE NOTA CREDITO ENCL137 - DE LAS FACTURA CLFV21377 | J144: CRUCE DE NOTA CREDITO ENCL137 - DE LAS FACTURA CLFV21377 | K144: CORREAGRO S.A. | M144: DSF | O144: =+MONTH(H144) -> 4 | P144: =+VLOOKUP(O144,X:Y,2,0) -> Abril
C145: 5502 - COMISIONES | D145: 53051501 | E145: COMISIONES BANCARIAS | F145: 3529 | G145: NIP-00016978 | H145: 45761 | I145: CONTABILIZACION IVA COMISION 4*1000 | J145: CONTABILIZACION IVA COMISION 4*1000 | K145: BANCOLOMBIA | O145: =+MONTH(H145) -> 4 | P145: =+VLOOKUP(O145,X:Y,2,0) -> Abril
C146: 5502 - COMISIONES | D146: 53051501 | E146: COMISIONES BANCARIAS | F146: 1802342 | G146: DSF-00001149 | H146: 45762 | I146: GASTOS BANCARIOS CORRESPONDIENTES AL MES DE MARZO 2025 | J146: GASTOS BANCARIOS CORRESPONDIENTES AL MES DE MARZO 2025 | K146: BANCO DE BOGOTA | O146: =+MONTH(H146) -> 4 | P146: =+VLOOKUP(O146,X:Y,2,0) -> Abril
C147: 5502 - COMISIONES | D147: 53051501 | E147: COMISIONES BANCARIAS | F147: 3990367.2 | G147: DSF-00001151 | H147: 45762 | I147: GASTOS BANCARIOS CORRESPONDIENTES AL MES DE MARZO 2025 | J147: GASTOS BANCARIOS CORRESPONDIENTES AL MES DE MARZO 2025 | K147: BANCOLOMBIA | O147: =+MONTH(H147) -> 4 | P147: =+VLOOKUP(O147,X:Y,2,0) -> Abril
C148: 5502 - COMISIONES | D148: 53051501 | E148: COMISIONES BANCARIAS | F148: 8069844 | G148: DSF-00001152 | H148: 45762 | I148: GASTOS BANCARIOS CORRESPONDIENTES AL MES DE MARZO 2025 | J148: GASTOS BANCARIOS CORRESPONDIENTES AL MES DE MARZO 2025 | K148: BANCO DAVIVIENDA S.A | O148: =+MONTH(H148) -> 4 | P148: =+VLOOKUP(O148,X:Y,2,0) -> Abril
C149: 5502 - COMISIONES | D149: 53051501 | E149: COMISIONES BANCARIAS | F149: 12052 | G149: DSF-00001153 | H149: 45762 | I149: GASTOS BANCARIOS CORRESPONDIENTES AL MES DE MARZO 2025 | J149: GASTOS BANCARIOS CORRESPONDIENTES AL MES DE MARZO 2025 | K149: BANCO AGRARIO DE COLOMBIA S.A | O149: =+MONTH(H149) -> 4 | P149: =+VLOOKUP(O149,X:Y,2,0) -> Abril
C150: 5502 - COMISIONES | D150: 53051501 | E150: COMISIONES BANCARIAS | F150: 15900 | G150: DSF-00001154 | H150: 45762 | I150: GASTOS BANCARIOS CORRESPONDIENTES AL MES DE MARZO 2025 | J150: GASTOS BANCARIOS CORRESPONDIENTES AL MES DE MARZO 2025 | K150: BANCO POPULAR | O150: =+MONTH(H150) -> 4 | P150: =+VLOOKUP(O150,X:Y,2,0) -> Abril
C151: 5502 - COMISIONES | D151: 53051501 | E151: COMISIONES BANCARIAS | F151: 1423500 | G151: DSF-00001156 | H151: 45762 | I151: GASTOS BANCARIOS CORRESPONDIENTES AL MES DE MARZO 2025 | J151: GASTOS BANCARIOS CORRESPONDIENTES AL MES DE MARZO 2025 | K151: ALIANZA FIDUCIARIA S.A | O151: =+MONTH(H151) -> 4 | P151: =+VLOOKUP(O151,X:Y,2,0) -> Abril
C152: 5502 - COMISIONES | D152: 53051501 | E152: COMISIONES BANCARIAS | F152: 846982.5 | G152: DSF-00001157 | H152: 45762 | I152: GASTOS BANCARIOS CORRESPONDIENTES AL MES DE MARZO 2025 | J152: GASTOS BANCARIOS CORRESPONDIENTES AL MES DE MARZO 2025 | K152: SERVICIOS FINANCIEROS S.A. SERFINANZA CIA DE FINANCIAMIENTO | O152: =+MONTH(H152) -> 4 | P152: =+VLOOKUP(O152,X:Y,2,0) -> Abril
C153: 5502 - COMISIONES | D153: 53051501 | E153: COMISIONES BANCARIAS | F153: 66033154 | G153: DSF-00001158 | H153: 45762 | I153: GASTOS BANCARIOS CORRESPONDIENTE AL MES DE MARZO 2025 | J153: GASTOS BANCARIOS CORRESPONDIENTE AL MES DE MARZO 2025 | K153: BBVA COLOMBIA S.A. | O153: =+MONTH(H153) -> 4 | P153: =+VLOOKUP(O153,X:Y,2,0) -> Abril
C154: 5502 - COMISIONES | D154: 53051501 | E154: COMISIONES BANCARIAS | F154: 4270500 | G154: DSF-00001159 | H154: 45762 | I154: GASTOS BANCARIOS CORRESPONDIENTES AL MES DE MARZO 2025 | J154: GASTOS BANCARIOS CORRESPONDIENTES AL MES DE MARZO 2025 | K154: FIDUCIARIA POPULAR S.A. | O154: =+MONTH(H154) -> 4 | P154: =+VLOOKUP(O154,X:Y,2,0) -> Abril
C155: 5502 - COMISIONES | D155: 53051501 | E155: COMISIONES BANCARIAS | F155: 3558750.5 | G155: DSF-00001160 | H155: 45762 | I155: GASTOS BANCARIOS CORRESPONDIENTES AL MES DE MARZO 2025 | J155: GASTOS BANCARIOS CORRESPONDIENTES AL MES DE MARZO 2025 | K155: FIDUCIARIA DAVIVIENDA S.A | O155: =+MONTH(H155) -> 4 | P155: =+VLOOKUP(O155,X:Y,2,0) -> Abril
C156: 5502 - COMISIONES | D156: 53051501 | E156: COMISIONES BANCARIAS | F156: 475395.51 | G156: DSF-00001161 | H156: 45762 | I156: GASTOS BANCARIOS CORRESPONDIENTES AL MES DE MARZO 2025 | J156: GASTOS BANCARIOS CORRESPONDIENTES AL MES DE MARZO 2025 | K156: BANCOLOMBIA PANAMA | O156: =+MONTH(H156) -> 4 | P156: =+VLOOKUP(O156,X:Y,2,0) -> Abril
... C440: 5502 - COMISIONES | D440: 53051501 | E440: COMISIONES BANCARIAS | F440: 3529 | G440: NIP-00017584 | H440: 45902 | I440: CONTABILIZAION IVA COMISION 4*1000 | J440: CONTABILIZAION IVA COMISION 4*1000 | K440: BANCOLOMBIA | O440: =+MONTH(H440) -> 9 | P440: =+VLOOKUP(O440,X:Y,2,0) -> Septiembre
C441: 5502 - COMISIONES | D441: 53051501 | E441: COMISIONES BANCARIAS | F441: 3529 | G441: NIP-00017616 | H441: 45908 | I441: SE CONTABILIZA IVA COMISION 4*1000 | J441: SE CONTABILIZA IVA COMISION 4*1000 | K441: BANCOLOMBIA | O441: =+MONTH(H441) -> 9 | P441: =+VLOOKUP(O441,X:Y,2,0) -> Septiembre | T441: BANCOLOMBIA
C442: 5502 - COMISIONES | D442: 53051501 | E442: COMISIONES BANCARIAS | F442: 13140 | G442: NIB-00007561 | H442: 45909 | I442: PAGO DE DEPSITOS JUDICIALES - ICSA | J442: PAGO DE DEPSITOS JUDICIALES - ICSA | K442: BANCO AGRARIO DE COLOMBIA S.A | O442: =+MONTH(H442) -> 9 | P442: =+VLOOKUP(O442,X:Y,2,0) -> Septiembre
C443: 5502 - COMISIONES | D443: 53051501 | E443: COMISIONES BANCARIAS | F443: 4428310.2 | G443: NIC-00038534 | H443: 45912 | K443: BBVA COLOMBIA S.A. | O443: =+MONTH(H443) -> 9 | P443: =+VLOOKUP(O443,X:Y,2,0) -> Septiembre
C444: 5502 - COMISIONES | D444: 53051501 | E444: COMISIONES BANCARIAS | F444: 3529 | G444: NIP-00017682 | H444: 45916 | I444: CONTABILIZACION IVA COMIISON 4*1000 | J444: CONTABILIZACION IVA COMIISON 4*1000 | K444: BANCOLOMBIA | O444: =+MONTH(H444) -> 9 | P444: =+VLOOKUP(O444,X:Y,2,0) -> Septiembre
C445: 5502 - COMISIONES | D445: 53051501 | E445: COMISIONES BANCARIAS | F445: 13140 | G445: DSF-00001407 | H445: 45917 | I445: GASTOS BANCARIOS CORRESPONDIENTE AL MES DE AGOSTO 2025 | J445: GASTOS BANCARIOS CORRESPONDIENTE AL MES DE AGOSTO 2025 | K445: BANCO AGRARIO DE COLOMBIA S.A | O445: =+MONTH(H445) -> 9 | P445: =+VLOOKUP(O445,X:Y,2,0) -> Septiembre
C446: 5502 - COMISIONES | D446: 53051501 | E446: COMISIONES BANCARIAS | F446: 3558750.4 | G446: FAC-00048354 | H446: 45917 | I446: SOC91016 - COMISION POR ADMINISTRACION- PERIODO DE FACTRUAUCION: SEPTIEMBRE 2025 | J446: SOC91016 - COMISION POR ADMINISTRACION- PERIODO DE FACTRUAUCION: SEPTIEMBRE 2025 | K446: FIDUCIARIA DAVIVIENDA S.A | O446: =+MONTH(H446) -> 9 | P446: =+VLOOKUP(O446,X:Y,2,0) -> Septiembre
C447: 5502 - COMISIONES | D447: 53051501 | E447: COMISIONES BANCARIAS | F447: 1 | G447: DSF-00001415 | H447: 45918 | I447: PRUEBA | J447: PRUEBA | K447: BANCO DE BOGOTA | O447: =+MONTH(H447) -> 9 | P447: =+VLOOKUP(O447,X:Y,2,0) -> Septiembre
C448: 5502 - COMISIONES | D448: 53051501 | E448: COMISIONES BANCARIAS | F448: 1 | G448: DSF-00001416 | H448: 45918 | I448: PRUEBA | J448: PRUEBA | K448: BANCO DE BOGOTA | O448: =+MONTH(H448) -> 9 | P448: =+VLOOKUP(O448,X:Y,2,0) -> Septiembre
C449: 5502 - COMISIONES | D449: 53051501 | E449: COMISIONES EN BOLSA | F449: 23705 | G449: NIP-00017694 | H449: 45918 | I449: CLFV23467 - SERV MODIFICACION BMC 860071250 | J449: CLFV23467 - SERV MODIFICACION BMC 860071250 | K449: CORREAGRO S.A. | O449: =+MONTH(H449) -> 9 | P449: =+VLOOKUP(O449,X:Y,2,0) -> Septiembre
C450: 5502 - COMISIONES | D450: 53051501 | E450: COMISIONES BANCARIAS | F450: 168067.23 | G450: NIB-00007661 | H450: 45919 | I450: FACTORING KLYM FAC-32176-32212 COMISION PAGO | J450: FACTORING KLYM FAC-32176-32212 COMISION PAGO | K450: KLYM S.A.S | O450: =+MONTH(H450) -> 9 | P450: =+VLOOKUP(O450,X:Y,2,0) -> Septiembre
C451: 5502 - COMISIONES | D451: 53051501 | E451: COMISIONES BANCARIAS | F451: 80000 | G451: CAM-00001009 | H451: 45922 | I451: PAGO DE COMISION DE CHEQUES BANCOLOMBIA ,(412624452-579274497-016926301-133925799) | J451: CAM1009 - LEGALIZACION DE CAJA MENOR OFICINA DE CALI DEL 02 AL 16 DE SEPTIEMBRE 2025 | K451: BANCOLOMBIA | O451: =+MONTH(H451) -> 9 | P451: =+VLOOKUP(O451,X:Y,2,0) -> Septiembre
C452: 5502 - COMISIONES | D452: 53051501 | E452: COMISIONES BANCARIAS | F452: 3529 | G452: NIP-00017701 | H452: 45922 | I452: CONTABILIZAICON IVA COMISION 4*1000 | J452: CONTABILIZAICON IVA COMISION 4*1000 | K452: BANCOLOMBIA | O452: =+MONTH(H452) -> 9 | P452: =+VLOOKUP(O452,X:Y,2,0) -> Septiembre
C453: 5502 - COMISIONES | D453: 53051501 | E453: COMISIONES BANCARIAS | F453: 3529 | G453: NIP-00017705 | H453: 45923 | I453: contabilizacion iva comision 4*1000 | J453: contabilizacion iva comision 4*1000 | K453: BANCOLOMBIA | O453: =+MONTH(H453) -> 9 | P453: =+VLOOKUP(O453,X:Y,2,0) -> Septiembre
C454: 5502 - COMISIONES | D454: 53051501 | E454: COMISIONES BANCARIAS | F454: 3529 | G454: NIP-00017709 | H454: 45924 | I454: CONTABILIZAICON IVA COMISON 4*1000 | J454: CONTABILIZAICON IVA COMISON 4*1000 | K454: BANCOLOMBIA | O454: =+MONTH(H454) -> 9 | P454: =+VLOOKUP(O454,X:Y,2,0) -> Septiembre
C455: 5502 - COMISIONES | D455: 53051501 | E455: COMISIONES BANCARIAS | F455: 1733196 | G455: DSF-00001430 | H455: 45926 | I455: GASTOS BANCARIOS CORRESPONDIENTE AL MES DE AOSTO 2025 | J455: GASTOS BANCARIOS CORRESPONDIENTE AL MES DE AOSTO 2025 | K455: BANCO DE BOGOTA | O455: =+MONTH(H455) -> 9 | P455: =+VLOOKUP(O455,X:Y,2,0) -> Septiembre
... C488: 5502 - COMISIONES | D488: 53051502 | E488: COMISIONES POR FACTORING | F488: 884743 | G488: NIB-00007710 | H488: 45912 | I488: FACTORING FAN-32014 COMISION PAGO | J488: FACTORING FAN-32014 COMISION PAGO | K488: BANCO DAVIVIENDA S.A | O488: =+MONTH(H488) -> 9 | P488: =+VLOOKUP(O488,X:Y,2,0) -> Septiembre
C489: 5502 - COMISIONES | D489: 53051502 | E489: COMISIONES POR FACTORING | F489: 46412961 | G489: NIC-00038534 | H489: 45912 | K489: BBVA COLOMBIA S.A. | O489: =+MONTH(H489) -> 9 | P489: =+VLOOKUP(O489,X:Y,2,0) -> Septiembre
C490: 5502 - COMISIONES | D490: 53051502 | E490: COMISIONES POR FACTORING | F490: 5053878 | G490: NIC-00038534 | H490: 45912 | K490: BANCO DAVIVIENDA S.A | O490: =+MONTH(H490) -> 9 | P490: =+VLOOKUP(O490,X:Y,2,0) -> Septiembre
C491: 5502 - COMISIONES | D491: 53051502 | E491: COMISIONES POR FACTORING | F491: 3048560.2 | G491: NIC-00038534 | H491: 45912 | K491: BANCOLOMBIA | O491: =+MONTH(H491) -> 9 | P491: =+VLOOKUP(O491,X:Y,2,0) -> Septiembre
C492: 5502 - COMISIONES | D492: 53051502 | E492: COMISIONES POR FACTORING | F492: 3627582.2 | G492: NIB-00007714 | H492: 45915 | I492: FACTORING FAN-31834-32065 COMISION PAGO | J492: FACTORING FAN-31834-32065 COMISION PAGO | K492: KLYM S.A.S | O492: =+MONTH(H492) -> 9 | P492: =+VLOOKUP(O492,X:Y,2,0) -> Septiembre
C493: 5502 - COMISIONES | D493: 53051502 | E493: COMISIONES POR FACTORING | F493: 7954700.4 | G493: NIB-00007660 | H493: 45919 | I493: FACTORING BBVA FAN-31287-31286 COMISION Y PAGO | J493: FACTORING BBVA FAN-31287-31286 COMISION Y PAGO | K493: BBVA COLOMBIA S.A. | O493: =+MONTH(H493) -> 9 | P493: =+VLOOKUP(O493,X:Y,2,0) -> Septiembre
C494: 5502 - COMISIONES | D494: 53051502 | E494: COMISIONES POR FACTORING | F494: 4657397 | G494: NIB-00007661 | H494: 45919 | I494: FACTORING KLYM FAC-32176-32212 COMISION PAGO | J494: FACTORING KLYM FAC-32176-32212 COMISION PAGO | K494: KLYM S.A.S | O494: =+MONTH(H494) -> 9 | P494: =+VLOOKUP(O494,X:Y,2,0) -> Septiembre
C495: 5502 - COMISIONES | D495: 53051502 | E495: COMISIONES POR FACTORING | F495: 4406293 | G495: NIB-00007662 | H495: 45919 | I495: FACTORING RED CAPITAL - FAN-32046-32126-32152-32175-32178 COMISION PAGO | J495: FACTORING RED CAPITAL - FAN-32046-32126-32152-32175-32178 COMISION PAGO | K495: BANCO DAVIVIENDA S.A | O495: =+MONTH(H495) -> 9 | P495: =+VLOOKUP(O495,X:Y,2,0) -> Septiembre
C496: 5502 - COMISIONES | D496: 53051502 | E496: COMISIONES POR FACTORING | F496: 11581864 | G496: NIB-00007716 | H496: 45925 | I496: FACTORING AJOVER FAN-32271 ALPINA FAN-32177-32192-32230-32258 PAGO COMISION | J496: FACTORING AJOVER FAN-32271 ALPINA FAN-32177-32192-32230-32258 PAGO COMISION | K496: KLYM S.A.S | O496: =+MONTH(H496) -> 9 | P496: =+VLOOKUP(O496,X:Y,2,0) -> Septiembre
C497: 5502 - COMISIONES | D497: 53051502 | E497: COMISIONES POR FACTORING | F497: 1427631 | G497: NIB-00007705 | H497: 45930 | I497: FACTORING FAN-31819 COMISION Y PAGO | J497: FACTORING FAN-31819 COMISION Y PAGO | K497: BANCOLOMBIA | O497: =+MONTH(H497) -> 9 | P497: =+VLOOKUP(O497,X:Y,2,0) -> Septiembre
C498: 5502 - COMISIONES | D498: 53051502 | E498: COMISIONES POR FACTORING | F498: 5864771 | G498: NIB-00007706 | H498: 45930 | I498: FACTORING FAN-32402-32403-32404 | J498: FACTORING FAN-32402-32403-32404 | K498: BANCOLOMBIA | O498: =+MONTH(H498) -> 9 | P498: =+VLOOKUP(O498,X:Y,2,0) -> Septiembre
C499: 5502 - COMISIONES | D499: 53051502 | E499: COMISIONES POR FACTORING | F499: 3589614.9 | G499: NIB-00007718 | H499: 45930 | I499: FACTORING FAN-32000 COMISION PAGO | J499: FACTORING FAN-32000 COMISION PAGO | K499: BBVA COLOMBIA S.A. | O499: =+MONTH(H499) -> 9 | P499: =+VLOOKUP(O499,X:Y,2,0) -> Septiembre
C500: 5502 - COMISIONES | D500: 53051502 | E500: COMISIONES POR FACTORING | F500: 12668289 | G500: NIB-00007719 | H500: 45930 | I500: FACTORING FAN- 32280-32282-32260 COMISION - PAGO | J500: FACTORING FAN- 32280-32282-32260 COMISION - PAGO | K500: BBVA COLOMBIA S.A. | O500: =+MONTH(H500) -> 9 | P500: =+VLOOKUP(O500,X:Y,2,0) -> Septiembre
C501: 5502 - COMISIONES | D501: 53051502 | E501: COMISIONES POR FACTORING | F501: 5083142.6 | G501: NIB-00007720 | H501: 45930 | I501: FACTORING FAN-32248 COMISION PAGO | J501: FACTORING FAN-32248 COMISION PAGO | K501: BBVA COLOMBIA S.A. | O501: =+MONTH(H501) -> 9 | P501: =+VLOOKUP(O501,X:Y,2,0) -> Septiembre
C502: 5502 - COMISIONES | D502: 53051502 | E502: COMISIONES POR FACTORING | F502: -65666624 | G502: NIC-00038753 | H502: 45930 | I502: RECLASIFICACION COMISIONES FACTORING VENCIMIENTOS OCTUBRE | J502: RECLASIFICACION COMISIONES FACTORING VENCIMIENTOS OCTUBRE | K502: BBVA COLOMBIA S.A. | O502: =+MONTH(H502) -> 9 | P502: =+VLOOKUP(O502,X:Y,2,0) -> Septiembre
C503: 5502 - COMISIONES | D503: 53051502 | E503: COMISIONES POR FACTORING | F503: -5291036 | G503: NIC-00038753 | H503: 45930 | I503: RECLASIFICACION COMISIONES FACTORING VENCIMIENTOS OCTUBRE | J503: RECLASIFICACION COMISIONES FACTORING VENCIMIENTOS OCTUBRE | K503: BANCO DAVIVIENDA S.A | O503: =+MONTH(H503) -> 9 | P503: =+VLOOKUP(O503,X:Y,2,0) -> Septiembre
... C657: 5502 - COMISIONES | D657: 53051501 | E657: COMISIONES EN BOLSA | F657: 21256229 | G657: NIP-00018162 | H657: 46022 | I657: CLFV24816 : COMSIION CORREAGRO - SERV DE REGISTRO BMC | J657: CLFV24816 : COMSIION CORREAGRO - SERV DE REGISTRO BMC | K657: CORREAGRO S.A. | O657: =+MONTH(H657) -> 12 | P657: =+VLOOKUP(O657,X:Y,2,0) -> Diciembre

Sheet COMISIONES
A1: CUENTA | B1: Auxiliar | C1: Desc. auxiliar | D1: Débitos | E1: Créditos | F1: Neto | G1: C.Costo | H1: Desc. C.Costo | I1: SECCION | J1: Fecha | K1: Docto. | L1: Notas | M1: Notas docto | N1: Nit tercero | O1: Razón social tercero docto. | P1: Nit movto. | Q1: Razón social tercero movto. | R1: Referencia 1 | S1: Referencia 2 | T1: Referencia 3 | U1: SUB SUBCUENTA | V1: Prefijo tipo docto | W1: Mes | X1: Nombre Mes
A2: 5502 - COMISIONES | B2: 53051501 | C2: BANCOS COMISIONES | D2: 2190 | E2: 0 | F2: 2190 | J2: 45664 | K2: NIB-00005736 | L2: PAGO DE DEPOSITOS JUDICIALES - COMPROBANTE DE PAGO: 1491465 - ARCHIVO: 30030 - INGENIO CARMELITA - ARCHIVO: GD20250107018919001961 | M2: PAGO DE DEPOSITOS JUDICIALES - COMPROBANTE DE PAGO: 1491465 - ARCHIVO: 30030 - INGENIO CARMELITA - ARCHIVO: GD20250107018919001961 | N2: 899999047 | O2: BANCO AGRARIO DE COLOMBIA | P2: 899999047 | Q2: BANCO AGRARIO DE COLOMBIA | W2: =+MONTH(J2) -> 1 | X2: =+ VLOOKUP(W2,'COMISIONES ENERO-MARZO 2025 (2)'!X:Y,2,0) -> Enero
A3: 5502 - COMISIONES | B3: 53051501 | C3: BANCOS COMISIONES | D3: 3529 | E3: 0 | F3: 3529 | J3: 45665 | K3: NIP-00016497 | L3: CONTABILIZACIÓN IVA COMISON 4*1000 | M3: CONTABILIZACIÓN IVA COMISON 4*1000 | N3: 16502466 | O3: SANTACRUZ JOHN | P3: 890903938 | Q3: BANCOLOMBIA | W3: =+MONTH(J3) -> 1 | X3: =+ VLOOKUP(W3,'COMISIONES ENERO-MARZO 2025 (2)'!X:Y,2,0) -> Enero
A4: 5502 - COMISIONES | B4: 53051501 | C4: BANCOS COMISIONES | D4: 7058 | E4: 0 | F4: 7058 | J4: 45665 | K4: NIP-00016498 | L4: CONTABILIZACIÓN IVA COMISON 4*1000 | M4: CONTABILIZACIÓN IVA COMISON 4*1000 | N4: 29760690 | O4: MORIONES SUAREZ BEATRIZ EUGENIA | P4: 890903938 | Q4: BANCOLOMBIA | W4: =+MONTH(J4) -> 1 | X4: =+ VLOOKUP(W4,'COMISIONES ENERO-MARZO 2025 (2)'!X:Y,2,0) -> Enero
A5: 5502 - COMISIONES | B5: 53051501 | C5: BANCOS COMISIONES | D5: 3529 | E5: 0 | F5: 3529 | J5: 45671 | K5: NIP-00016519 | L5: CONTABILIZACIÓN IVA COMISION 4*1000 | M5: CONTABILIZACIÓN IVA COMISION 4*1000 | N5: 16502466 | O5: SANTACRUZ JOHN | P5: 890903938 | Q5: BANCOLOMBIA | W5: =+MONTH(J5) -> 1 | X5: =+ VLOOKUP(W5,'COMISIONES ENERO-MARZO 2025 (2)'!X:Y,2,0) -> Enero
A6: 5502 - COMISIONES | B6: 53051501 | C6: BANCOS COMISIONES | D6: 2650 | E6: 0 | F6: 2650 | J6: 45674 | K6: NIB-00005915 | L6: GASTOS BANCARIOS POPULAR 2276 MES DE ENERO 2025 | M6: GASTOS BANCARIOS POPULAR 2276 MES DE ENERO 2025 | N6: 860007738 | O6: BANCO POPULAR | P6: 860007738 | Q6: BANCO POPULAR | W6: =+MONTH(J6) -> 1 | X6: =+ VLOOKUP(W6,'COMISIONES ENERO-MARZO 2025 (2)'!X:Y,2,0) -> Enero
A7: 5502 - COMISIONES | B7: 53051501 | C7: BANCOS COMISIONES | D7: 3529 | E7: 0 | F7: 3529 | J7: 45678 | K7: NIP-00016556 | L7: CONTAN¿BILIZACIÓN IVA 4*1000 COMISION | M7: CONTAN¿BILIZACIÓN IVA 4*1000 COMISION | N7: 16502466 | O7: SANTACRUZ JOHN | P7: 890903938 | Q7: BANCOLOMBIA | W7: =+MONTH(J7) -> 1 | X7: =+ VLOOKUP(W7,'COMISIONES ENERO-MARZO 2025 (2)'!X:Y,2,0) -> Enero
A8: 5502 - COMISIONES | B8: 53051501 | C8: BANCOS COMISIONES | D8: 3529 | E8: 0 | F8: 3529 | J8: 45679 | K8: NIP-00016562 | L8: contabilización iva comision 4*1000 | M8: contabilización iva comision 4*1000 | N8: 1112300106 | O8: NINO PALOMINO CARLOS MARIO | P8: 890903938 | Q8: BANCOLOMBIA | W8: =+MONTH(J8) -> 1 | X8: =+ VLOOKUP(W8,'COMISIONES ENERO-MARZO 2025 (2)'!X:Y,2,0) -> Enero
A9: 5502 - COMISIONES | B9: 53051501 | C9: BANCOS COMISIONES | D9: 3529 | E9: 0 | F9: 3529 | J9: 45684 | K9: NIP-00016588 | L9: CONTABILIZACIÓN IVA COMISION 4*1000 | M9: CONTABILIZACIÓN IVA COMISION 4*1000 | N9: 1144185697 | O9: REYES MORIONES ANGELICA | P9: 890903938 | Q9: BANCOLOMBIA | W9: =+MONTH(J9) -> 1 | X9: =+ VLOOKUP(W9,'COMISIONES ENERO-MARZO 2025 (2)'!X:Y,2,0) -> Enero
A10: 5502 - COMISIONES | B10: 53051501 | C10: BANCOS COMISIONES | D10: 38140 | E10: 0 | F10: 38140 | J10: 45686 | K10: DSF-00001059 | L10: GASTOS BANCARIOS 27 AL 31 DICIEMBRE 2024 -BGTA CALI | M10: GASTOS BANCARIOS 27 AL 31 DICIEMBRE 2024 | N10: 860002964 | O10: BANCO DE BOGOTA | P10: 860002964 | Q10: BANCO DE BOGOTA | V10: DSF | W10: =+MONTH(J10) -> 1 | X10: =+ VLOOKUP(W10,'COMISIONES ENERO-MARZO 2025 (2)'!X:Y,2,0) -> Enero
A11: 5502 - COMISIONES | B11: 53051501 | C11: BANCOS COMISIONES | D11: 78520 | E11: 0 | F11: 78520 | J11: 45686 | K11: DSF-00001059 | L11: GASTOS BANCARIOS 27 AL 31 DICIEMBRE 2024 -BGTA TULUA | M11: GASTOS BANCARIOS 27 AL 31 DICIEMBRE 2024 | N11: 860002964 | O11: BANCO DE BOGOTA | P11: 860002964 | Q11: BANCO DE BOGOTA | V11: DSF | W11: =+MONTH(J11) -> 1 | X11: =+ VLOOKUP(W11,'COMISIONES ENERO-MARZO 2025 (2)'!X:Y,2,0) -> Enero
A12: 5502 - COMISIONES | B12: 53051501 | C12: BANCOS COMISIONES | D12: 2500 | E12: 0 | F12: 2500 | J12: 45686 | K12: DSF-00001060 | L12: GASTOS BANCARIOS 27 AL 31 DICIEMBRE 2024 -POPULAR 2276 | M12: GASTOS BANCARIOS 27 AL 31 DICIEMBRE 2024 -POPULAR 2276 | N12: 860007738 | O12: BANCO POPULAR | P12: 860007738 | Q12: BANCO POPULAR | V12: DSF | W12: =+MONTH(J12) -> 1 | X12: =+ VLOOKUP(W12,'COMISIONES ENERO-MARZO 2025 (2)'!X:Y,2,0) -> Enero
A13: 5502 - COMISIONES | B13: 53051501 | C13: BANCOS COMISIONES | D13: 125906.09 | E13: 0 | F13: 125906.09 | J13: 45686 | K13: DSF-00001061 | L13: GASTOS BANCARIOS 27 AL 31 DICIEMBRE 2024 -BANCOLOMBIA 801 | M13: GASTOS BANCARIOS 27 AL 31 DICIEMBRE 2024 -BANCOLOMBIA | N13: 890903938 | O13: BANCOLOMBIA | P13: 890903938 | Q13: BANCOLOMBIA | V13: DSF | W13: =+MONTH(J13) -> 1 | X13: =+ VLOOKUP(W13,'COMISIONES ENERO-MARZO 2025 (2)'!X:Y,2,0) -> Enero
A14: 5502 - COMISIONES | B14: 53051501 | C14: BANCOS COMISIONES | D14: 16560 | E14: 0 | F14: 16560 | J14: 45686 | K14: DSF-00001061 | L14: GASTOS BANCARIOS 27 AL 31 DICIEMBRE 2024 -BANCOLOMBIA ESPECIAL | M14: GASTOS BANCARIOS 27 AL 31 DICIEMBRE 2024 -BANCOLOMBIA | N14: 890903938 | O14: BANCOLOMBIA | P14: 890903938 | Q14: BANCOLOMBIA | V14: DSF | W14: =+MONTH(J14) -> 1 | X14: =+ VLOOKUP(W14,'COMISIONES ENERO-MARZO 2025 (2)'!X:Y,2,0) -> Enero
A15: 5502 - COMISIONES | B15: 53051501 | C15: BANCOS COMISIONES | D15: 0 | E15: 125906.09 | F15: -125906.09 | J15: 45686 | K15: NIC-00035976 | L15: GASTOS BANCARIOS 27 AL 31 DICIEMBRE 2024 -BANCOLOMBIA 801 | M15: DEVOLUCION DE DSF 1059-1060-1061 - GASTOS BANCARIOS 27 AL 31 DIC 2024 | N15: 891900196 | O15: INGENIO CARMELITA S.A. | P15: 890903938 | Q15: BANCOLOMBIA | W15: =+MONTH(J15) -> 1 | X15: =+ VLOOKUP(W15,'COMISIONES ENERO-MARZO 2025 (2)'!X:Y,2,0) -> Enero
A16: 5502 - COMISIONES | B16: 53051501 | C16: BANCOS COMISIONES | D16: 0 | E16: 16560 | F16: -16560 | J16: 45686 | K16: NIC-00035976 | L16: GASTOS BANCARIOS 27 AL 31 DICIEMBRE 2024 -BANCOLOMBIA ESPECIAL | M16: DEVOLUCION DE DSF 1059-1060-1061 - GASTOS BANCARIOS 27 AL 31 DIC 2024 | N16: 891900196 | O16: INGENIO CARMELITA S.A. | P16: 890903938 | Q16: BANCOLOMBIA | W16: =+MONTH(J16) -> 1 | X16: =+ VLOOKUP(W16,'COMISIONES ENERO-MARZO 2025 (2)'!X:Y,2,0) -> Enero
A17: 5502 - COMISIONES | B17: 53051501 | C17: BANCOS COMISIONES | D17: 0 | E17: 38140 | F17: -38140 | J17: 45686 | K17: NIC-00035976 | L17: GASTOS BANCARIOS 27 AL 31 DICIEMBRE 2024 -BGTA CALI | M17: DEVOLUCION DE DSF 1059-1060-1061 - GASTOS BANCARIOS 27 AL 31 DIC 2024 | N17: 891900196 | O17: INGENIO CARMELITA S.A. | P17: 860002964 | Q17: BANCO DE BOGOTA | W17: =+MONTH(J17) -> 1 | X17: =+ VLOOKUP(W17,'COMISIONES ENERO-MARZO 2025 (2)'!X:Y,2,0) -> Enero
A18: 5502 - COMISIONES | B18: 53051501 | C18: BANCOS COMISIONES | D18: 0 | E18: 78520 | F18: -78520 | J18: 45686 | K18: NIC-00035976 | L18: GASTOS BANCARIOS 27 AL 31 DICIEMBRE 2024 -BGTA TULUA | M18: DEVOLUCION DE DSF 1059-1060-1061 - GASTOS BANCARIOS 27 AL 31 DIC 2024 | N18: 891900196 | O18: INGENIO CARMELITA S.A. | P18: 860002964 | Q18: BANCO DE BOGOTA | W18: =+MONTH(J18) -> 1 | X18: =+ VLOOKUP(W18,'COMISIONES ENERO-MARZO 2025 (2)'!X:Y,2,0) -> Enero
A19: 5502 - COMISIONES | B19: 53051501 | C19: BANCOS COMISIONES | D19: 0 | E19: 2500 | F19: -2500 | J19: 45686 | K19: NIC-00035976 | L19: GASTOS BANCARIOS 27 AL 31 DICIEMBRE 2024 -POPULAR 2276 | M19: DEVOLUCION DE DSF 1059-1060-1061 - GASTOS BANCARIOS 27 AL 31 DIC 2024 | N19: 891900196 | O19: INGENIO CARMELITA S.A. | P19: 860007738 | Q19: BANCO POPULAR | W19: =+MONTH(J19) -> 1 | X19: =+ VLOOKUP(W19,'COMISIONES ENERO-MARZO 2025 (2)'!X:Y,2,0) -> Enero
A20: 5502 - COMISIONES | B20: 53051501 | C20: BANCOS COMISIONES | D20: 3529 | E20: 0 | F20: 3529 | J20: 45686 | K20: NIP-00016610 | L20: contabilización de iva comision 4*1000 | M20: contabilización de iva comision 4*1000 | N20: 16502466 | O20: SANTACRUZ JOHN | P20: 890903938 | Q20: BANCOLOMBIA | W20: =+MONTH(J20) -> 1 | X20: =+ VLOOKUP(W20,'COMISIONES ENERO-MARZO 2025 (2)'!X:Y,2,0) -> Enero
A21: 5502 - COMISIONES | B21: 53051501 | C21: BANCOS COMISIONES | D21: 3558750 | E21: 0 | F21: 3558750 | J21: 45688 | K21: FAC-00045087 | L21: FAC132801 - COMISION FIDUCIARIA MES DE ENERO 2025- COMISION FIJA 2.5 SMMLV | M21: FAC132801 - COMISION FIDUCIARIA MES DE ENERO 2025- COMISION FIJA 2.5 SMMLV | N21: 800141235 | O21: FIDUCIARIA POPULAR S.A. | P21: 800141235 | Q21: FIDUCIARIA POPULAR S.A. | W21: =+MONTH(J21) -> 1 | X21: =+ VLOOKUP(W21,'COMISIONES ENERO-MARZO 2025 (2)'!X:Y,2,0) -> Enero
A22: 5502 - COMISIONES | B22: 53051501 | C22: BANCOS COMISIONES | D22: 3558750 | E22: 0 | F22: 3558750 | J22: 45688 | K22: FAC-00045088 | L22: SOC81109 - COMISION POR ADMINISTRACION MES DE ENERO 2025 - EA | M22: SOC81109 - COMISION POR ADMINISTRACION MES DE ENERO 2025 - EA | N22: 800182281 | O22: FIDUCIARIA DAVIVIENDA S.A | P22: 800182281 | Q22: FIDUCIARIA DAVIVIENDA S.A | W22: =+MONTH(J22) -> 1 | X22: =+ VLOOKUP(W22,'COMISIONES ENERO-MARZO 2025 (2)'!X:Y,2,0) -> Enero
A23: 5502 - COMISIONES | B23: 53051501 | C23: BANCOS COMISIONES | D23: 9600.49 | E23: 0 | F23: 9600.49 | J23: 45688 | K23: NIB-00005875 | L23: COSTO DE TRANSACCION -PAGO DE FACTURAS A NOMBRE DE INGENIERIA Y EQUIPOS PARA LA INGENIERIA | M23: PAGO DE FACTURAS A NOMBRE DE INGENIERIA Y EQUIPOS PARA LA INGENIERIA | N23: 890903938 | O23: BANCOLOMBIA | P23: 890903938 | Q23: BANCOLOMBIA | W23: =+MONTH(J23) -> 1 | X23: =+ VLOOKUP(W23,'COMISIONES ENERO-MARZO 2025 (2)'!X:Y,2,0) -> Enero
A24: 5502 - COMISIONES | B24: 53051501 | C24: BANCOS COMISIONES | D24: 1824 | E24: 0 | F24: 1824 | J24: 45688 | K24: NIB-00005875 | L24: IVA DE TRANSACCION -PAGO DE FACTURAS A NOMBRE DE INGENIERIA Y EQUIPOS PARA LA INGENIERIA | M24: PAGO DE FACTURAS A NOMBRE DE INGENIERIA Y EQUIPOS PARA LA INGENIERIA | N24: 890903938 | O24: BANCOLOMBIA | P24: 890903938 | Q24: BANCOLOMBIA | W24: =+MONTH(J24) -> 1 | X24: =+ VLOOKUP(W24,'COMISIONES ENERO-MARZO 2025 (2)'!X:Y,2,0) -> Enero
A25: 5502 - COMISIONES | B25: 53051501 | C25: BANCOS COMISIONES | D25: 3867500 | E25: 0 | F25: 3867500 | J25: 45688 | K25: NIB-00005899 | L25: COMISION FIJA MES DE ENERO 2025 | M25: GASTOS BANCARIOS MES DE ENERO 2025 FIDEICOMISO 42112858 - RENTA LIQUIDAN GASTOS BANCARIOS MES DE ENERO 2025 FIDEICOMISO 42112858 - RENTA LIQUIDA | N25: 800182281 | O25: FIDUCIARIA DAVIVIENDA S.A | P25: 800182281 | Q25: FIDUCIARIA DAVIVIENDA S.A | W25: =+MONTH(J25) -> 1 | X25: =+ VLOOKUP(W25,'COMISIONES ENERO-MARZO 2025 (2)'!X:Y,2,0) -> Enero
A26: 5502 - COMISIONES | B26: 53051501 | C26: BANCOS COMISIONES | D26: 514829.43 | E26: 0 | F26: 514829.43 | J26: 45688 | K26: NIB-00005902 | L26: GASTOS BANCARIOS MES DE ENERO 2025- BANCOLOMBIA PANAMA | M26: GASTOS BANCARIOS MES DE ENERO 2025- BANCOLOMBIA PANAMA | N26: 928149105971DV28 | O26: BANCOLOMBIA PANAMA | P26: 928149105971DV28 | Q26: BANCOLOMBIA PANAMA | W26: =+MONTH(J26) -> 1 | X26: =+ VLOOKUP(W26,'COMISIONES ENERO-MARZO 2025 (2)'!X:Y,2,0) -> Enero
A27: 5502 - COMISIONES | B27: 53051501 | C27: BANCOS COMISIONES | D27: 4280613 | E27: 0 | F27: 4280613 | J27: 45688 | K27: NIB-00005906 | L27: GASTOS BANCARIOS BOGOTA TULUA 612036319- MES DE ENERO 2025 | M27: GASTOS BANCARIOS BOGOTA TULUA 612036319- MES DE ENERO 2025 | N27: 860002964 | O27: BANCO DE BOGOTA | P27: 860002964 | Q27: BANCO DE BOGOTA | W27: =+MONTH(J27) -> 1 | X27: =+ VLOOKUP(W27,'COMISIONES ENERO-MARZO 2025 (2)'!X:Y,2,0) -> Enero
A28: 5502 - COMISIONES | B28: 53051501 | C28: BANCOS COMISIONES | D28: 4700320.5 | E28: 0 | F28: 4700320.5 | J28: 45688 | K28: NIB-00005911 | L28: GASTOS BANCARIOS BANCOLOMBIA CTA CTE 80104152201 - MES DE ENERO 2025 | M28: GASTOS BANCARIOS BANCOLOMBIA CTA CTE 80104152201 - MES DE ENERO 2025 | N28: 890903938 | O28: BANCOLOMBIA | P28: 890903938 | Q28: BANCOLOMBIA | W28: =+MONTH(J28) -> 1 | X28: =+ VLOOKUP(W28,'COMISIONES ENERO-MARZO 2025 (2)'!X:Y,2,0) -> Enero
A29: 5502 - COMISIONES | B29: 53051501 | C29: BANCOS COMISIONES | D29: 9801719 | E29: 0 | F29: 9801719 | J29: 45688 | K29: NIB-00005919 | L29: GASTOS BANCARIOS DAVIVIENDA 7678 MES DE ENERO 2025 | M29: GASTOS BANCARIOS DAVIVIENDA 7678 MES DE ENERO 2025 | N29: 860034313 | O29: DAVIVIENDA | P29: 860034313 | Q29: DAVIVIENDA | W29: =+MONTH(J29) -> 1 | X29: =+ VLOOKUP(W29,'COMISIONES ENERO-MARZO 2025 (2)'!X:Y,2,0) -> Enero
A30: 5502 - COMISIONES | B30: 53051501 | C30: BANCOS COMISIONES | D30: 22436 | E30: 0 | F30: 22436 | J30: 45688 | K30: NIB-00005936 | L30: GASTOS BANCARIOS BGTA CALI 256096355 MES DE ENERO 2025 | M30: GASTOS BANCARIOS BGTA CALI 256096355 MES DE ENERO 2025 | N30: 860002964 | O30: BANCO DE BOGOTA | P30: 860002964 | Q30: BANCO DE BOGOTA | W30: =+MONTH(J30) -> 1 | X30: =+ VLOOKUP(W30,'COMISIONES ENERO-MARZO 2025 (2)'!X:Y,2,0) -> Enero
A31: 5502 - COMISIONES | B31: 53051501 | C31: BANCOS COMISIONES | D31: 7087724.8 | E31: 0 | F31: 7087724.8 | J31: 45688 | K31: NIC-00036152 | L31: COMISIONES FACTORIGN TRULULU FAN-28253-255 SUPER ALIMENTOS 28207-225-261-262 | M31: reclasificacion de cuentas en comision Factoring con Bavaria y Trululu | N31: 860003020 | O31: BBVA COLOMBIA S.A. | P31: 860003020 | Q31: BBVA COLOMBIA S.A. | W31: =+MONTH(J31) -> 1 | X31: =+ VLOOKUP(W31,'COMISIONES ENERO-MARZO 2025 (2)'!X:Y,2,0) -> Enero
A32: 5502 - COMISIONES | B32: 53051501 | C32: BANCOS COMISIONES | D32: 36839957 | E32: 0 | F32: 36839957 | J32: 45688 | K32: NIC-00036152 | L32: REGISTRO COMISION FACTORING BBVA FAN-27806-848-849-850-862-863-864 | M32: reclasificacion de cuentas en comision Factoring con Bavaria y Trululu | N32: 860003020 | O32: BBVA COLOMBIA S.A. | P32: 860003020 | Q32: BBVA COLOMBIA S.A. | W32: =+MONTH(J32) -> 1 | X32: =+ VLOOKUP(W32,'COMISIONES ENERO-MARZO 2025 (2)'!X:Y,2,0) -> Enero
A33: 5502 - COMISIONES | B33: 53051501 | C33: BANCOS COMISIONES | D33: 3529 | E33: 0 | F33: 3529 | J33: 45692 | K33: NIC-00036050 | L33: CONTABILIZACIÓN IVA COMISION 4*1000 | M33: CONTABILIZACIÓN IVA COMISION 4*1000 | N33: 29760690 | O33: MORIONES SUAREZ BEATRIZ EUGENIA | P33: 890903938 | Q33: BANCOLOMBIA | W33: =+MONTH(J33) -> 2 | X33: =+ VLOOKUP(W33,'COMISIONES ENERO-MARZO 2025 (2)'!X:Y,2,0) -> Febrero
A34: 5502 - COMISIONES | B34: 53051501 | C34: BANCOS COMISIONES | D34: 3529 | E34: 0 | F34: 3529 | J34: 45692 | K34: NIC-00036051 | L34: CONTABILIZACIÓN IVA COMISION 4*1000 | M34: CONTABILIZACIÓN IVA COMISON 4*1000 | N34: 16502466 | O34: SANTACRUZ JOHN | P34: 890903938 | Q34: BANCOLOMBIA | W34: =+MONTH(J34) -> 2 | X34: =+ VLOOKUP(W34,'COMISIONES ENERO-MARZO 2025 (2)'!X:Y,2,0) -> Febrero
A35: 5502 - COMISIONES | B35: 53051501 | C35: BANCOS COMISIONES | D35: 3529 | E35: 0 | F35: 3529 | J35: 45692 | K35: NIC-00036053 | L35: CONTABILIZACIÓN IVA COMISION 4*1000 | M35: CONTABILIZACION IVA COMISON 4*1000 | N35: 1144185697 | O35: REYES MORIONES ANGELICA | P35: 890903938 | Q35: BANCOLOMBIA | W35: =+MONTH(J35) -> 2 | X35: =+ VLOOKUP(W35,'COMISIONES ENERO-MARZO 2025 (2)'!X:Y,2,0) -> Febrero
A36: 5502 - COMISIONES | B36: 53051501 | C36: BANCOS COMISIONES | D36: 11004 | E36: 0 | F36: 11004 | J36: 45695 | K36: NIB-00005978 | L36: PAGO DE DEPOSITOS JUCIALES ICSA - 1499295 - SECUENCIAL DEL ARCHIVO: GD202502070891001961_01.TXT | M36: PAGO DE DEPOSITOS JUCIALES ICSA - 1499295 - SECUENCIAL DEL ARCHIVO: GD202502070891001961_01.TXT | N36: 899999047 | O36: BANCO AGRARIO DE COLOMBIA | P36: 899999047 | Q36: BANCO AGRARIO DE COLOMBIA | W36: =+MONTH(J36) -> 2 | X36: =+ VLOOKUP(W36,'COMISIONES ENERO-MARZO 2025 (2)'!X:Y,2,0) -> Febrero
A37: 5502 - COMISIONES | B37: 53051501 | C37: BANCOS COMISIONES | D37: 9600 | E37: 0 | F37: 9600 | J37: 45702 | K37: NIB-00005995 | L37: PAGO DE DEPOSITOS JUDICIALES - INGENIERIA Y EQUIPOS PARA LA INDUSTRIA - CODIGO DEL JUZGADO 760012031004 - NUMEOR DE PROCESO 7600131030042023000800 | M37: PAGO DE DEPOSITOS JUDICIALES - INGENIERIA Y EQUIPOS PARA LA INDUSTRIA - CODIGO DEL JUZGADO 760012031004 - NUMEOR DE PROCESO 7600131030042023000800 | N37: 899999047 | O37: BANCO AGRARIO DE COLOMBIA | P37: 899999047 | Q37: BANCO AGRARIO DE COLOMBIA | W37: =+MONTH(J37) -> 2 | X37: =+ VLOOKUP(W37,'COMISIONES ENERO-MARZO 2025 (2)'!X:Y,2,0) -> Febrero
A38: 5502 - COMISIONES | B38: 53051501 | C38: BANCOS COMISIONES | D38: 3529 | E38: 0 | F38: 3529 | J38: 45702 | K38: NIP-00016714 | L38: CONTABILIZACIÓN IVA COMISION 4*1000 | M38: CONTABILIZACIÓN IVA COMISION 4*1000 | N38: 16502466 | O38: SANTACRUZ JOHN | P38: 890903938 | Q38: BANCOLOMBIA | W38: =+MONTH(J38) -> 2 | X38: =+ VLOOKUP(W38,'COMISIONES ENERO-MARZO 2025 (2)'!X:Y,2,0) -> Febrero
A39: 5502 - COMISIONES | B39: 53051501 | C39: BANCOS COMISIONES | D39: 3529 | E39: 0 | F39: 3529 | J39: 45706 | K39: NIP-00016723 | L39: CONTABILIZACIÓN IVA COMISON 4*1000 | M39: CONTABILIZACIÓN IVA COMISON 4*1000 | N39: 16502466 | O39: SANTACRUZ JOHN | P39: 890903938 | Q39: BANCOLOMBIA | W39: =+MONTH(J39) -> 2 | X39: =+ VLOOKUP(W39,'COMISIONES ENERO-MARZO 2025 (2)'!X:Y,2,0) -> Febrero
A40: 5502 - COMISIONES | B40: 53051501 | C40: BANCOS COMISIONES | D40: 4303049 | E40: 0 | F40: 4303049 | J40: 45707 | K40: DSF-00001074 | L40: GASTOS BANCARIOS CORRESPONDIENTES AL MES DE ENERO 2025 | M40: GASTOS BANCARIOS CORRESPONDIENTES AL MES DE ENERO 2025 | N40: 860002964 | O40: BANCO DE BOGOTA | P40: 860002964 | Q40: BANCO DE BOGOTA | V40: DSF | W40: =+MONTH(J40) -> 2 | X40: =+ VLOOKUP(W40,'COMISIONES ENERO-MARZO 2025 (2)'!X:Y,2,0) -> Febrero
A41: 5502 - COMISIONES | B41: 53051501 | C41: BANCOS COMISIONES | D41: 4739977 | E41: 0 | F41: 4739977 | J41: 45707 | K41: DSF-00001076 | L41: GASTOS BANCARIOS CORRESPONDIENTES AL MES DE ENERO 2025 | M41: GASTOS BANCARIOS CORRESPONDIENTES AL MES DE ENERO 2025 | N41: 890903938 | O41: BANCOLOMBIA | P41: 890903938 | Q41: BANCOLOMBIA | V41: DSF | W41: =+MONTH(J41) -> 2 | X41: =+ VLOOKUP(W41,'COMISIONES ENERO-MARZO 2025 (2)'!X:Y,2,0) -> Febrero
A42: 5502 - COMISIONES | B42: 53051501 | C42: BANCOS COMISIONES | D42: 9801719 | E42: 0 | F42: 9801719 | J42: 45707 | K42: DSF-00001077 | L42: GASTOS BANCARIOS CORRESPONDIENTES AL MES DE ENERO 2025 | M42: GASTOS BANCARIOS CORRESPONDIENTES AL MES DE ENERO 2025 | N42: 860034313 | O42: DAVIVIENDA | P42: 860034313 | Q42: DAVIVIENDA | V42: DSF | W42: =+MONTH(J42) -> 2 | X42: =+ VLOOKUP(W42,'COMISIONES ENERO-MARZO 2025 (2)'!X:Y,2,0) -> Febrero
A43: 5502 - COMISIONES | B43: 53051501 | C43: BANCOS COMISIONES | D43: 2190 | E43: 0 | F43: 2190 | J43: 45707 | K43: DSF-00001078 | L43: GASTOS BANCARIOS CORRESPONDIENTES AL MES DE ENERO 2025 | M43: GASTOS BANCARIOS CORRESPONDIENTES AL MES DE ENERO 2025 | N43: 800037800 | O43: BANCO AGRARIO DE COLOMBIA S.A | P43: 800037800 | Q43: BANCO AGRARIO DE COLOMBIA S.A | V43: DSF | W43: =+MONTH(J43) -> 2 | X43: =+ VLOOKUP(W43,'COMISIONES ENERO-MARZO 2025 (2)'!X:Y,2,0) -> Febrero
A44: 5502 - COMISIONES | B44: 53051501 | C44: BANCOS COMISIONES | D44: 2650 | E44: 0 | F44: 2650 | J44: 45707 | K44: DSF-00001079 | L44: GASTOS BANCARIOS CORRESPONDIENTES AL MES DE ENERO 2025 | M44: GASTOS BANCARIOS CORRESPONDIENTES AL MES DE ENERO 2025 | N44: 860007738 | O44: BANCO POPULAR | P44: 860007738 | Q44: BANCO POPULAR | V44: DSF | W44: =+MONTH(J44) -> 2 | X44: =+ VLOOKUP(W44,'COMISIONES ENERO-MARZO 2025 (2)'!X:Y,2,0) -> Febrero
A45: 5502 - COMISIONES | B45: 53051501 | C45: BANCOS COMISIONES | D45: 43927682 | E45: 0 | F45: 43927682 | J45: 45707 | K45: DSF-00001081 | L45: GASTOS BANCARIOS CORRESPONDIENTES AL MES DE ENERO 2025 | M45: GASTOS BANCARIOS CORRESPONDIENTES AL MES DE ENERO 2025 | N45: 860003020 | O45: BBVA COLOMBIA S.A. | P45: 860003020 | Q45: BBVA COLOMBIA S.A. | V45: DSF | W45: =+MONTH(J45) -> 2 | X45: =+ VLOOKUP(W45,'COMISIONES ENERO-MARZO 2025 (2)'!X:Y,2,0) -> Febrero
A46: 5502 - COMISIONES | B46: 53051501 | C46: BANCOS COMISIONES | D46: 3558750 | E46: 0 | F46: 3558750 | J46: 45707 | K46: DSF-00001082 | L46: GASTOS BANCARIOS CORRESPONDIENTES AL MES DE ENERO 2025 | M46: GASTOS BANCARIOS CORRESPONDIENTES AL MES DE ENERO 2025 | N46: 800141235 | O46: FIDUCIARIA POPULAR S.A. | P46: 800141235 | Q46: FIDUCIARIA POPULAR S.A. | V46: DSF | W46: =+MONTH(J46) -> 2 | X46: =+ VLOOKUP(W46,'COMISIONES ENERO-MARZO 2025 (2)'!X:Y,2,0) -> Febrero
A47: 5502 - COMISIONES | B47: 53051501 | C47: BANCOS COMISIONES | D47: 7426250 | E47: 0 | F47: 7426250 | J47: 45707 | K47: DSF-00001083 | L47: GASTOS BANCARIOS CORRESPONDIENTES AL MES DE ENERO 2025 | M47: GASTOS BANCARIOS CORRESPONDIENTES AL MES DE ENERO 2025 | N47: 800182281 | O47: FIDUCIARIA DAVIVIENDA S.A | P47: 800182281 | Q47: FIDUCIARIA DAVIVIENDA S.A | V47: DSF | W47: =+MONTH(J47) -> 2 | X47: =+ VLOOKUP(W47,'COMISIONES ENERO-MARZO 2025 (2)'!X:Y,2,0) -> Febrero
A48: 5502 - COMISIONES | B48: 53051501 | C48: BANCOS COMISIONES | D48: 514829.43 | E48: 0 | F48: 514829.43 | J48: 45707 | K48: DSF-00001084 | L48: GASTOS BANCARIOS CORRESPONDIENTES AL MES DE ENERO 2025 | M48: GASTOS BANCARIOS CORRESPONDIENTES AL MES DE ENERO 2025 | N48: 928149105971DV28 | O48: BANCOLOMBIA PANAMA | P48: 928149105971DV28 | Q48: BANCOLOMBIA PANAMA | V48: DSF | W48: =+MONTH(J48) -> 2 | X48: =+ VLOOKUP(W48,'COMISIONES ENERO-MARZO 2025 (2)'!X:Y,2,0) -> Febrero
A49: 5502 - COMISIONES | B49: 53051501 | C49: BANCOS COMISIONES | D49: 0 | E49: 2190 | F49: -2190 | J49: 45707 | K49: NIC-00036228 | L49: DEVOLUCION DE DSF - GASTOS BANCARIOS MES DE ENERO 2025 | M49: DEVOLUCION DE DSF - GASTOS BANCARIOS MES DE ENERO 2025 | N49: 891900196 | O49: INGENIO CARMELITA S.A. | P49: 800037800 | Q49: BANCO AGRARIO DE COLOMBIA S.A | W49: =+MONTH(J49) -> 2 | X49: =+ VLOOKUP(W49,'COMISIONES ENERO-MARZO 2025 (2)'!X:Y,2,0) -> Febrero
A50: 5502 - COMISIONES | B50: 53051501 | C50: BANCOS COMISIONES | D50: 0 | E50: 3558750 | F50: -3558750 | J50: 45707 | K50: NIC-00036228 | L50: DEVOLUCION DE DSF - GASTOS BANCARIOS MES DE ENERO 2025 | M50: DEVOLUCION DE DSF - GASTOS BANCARIOS MES DE ENERO 2025 | N50: 891900196 | O50: INGENIO CARMELITA S.A. | P50: 800141235 | Q50: FIDUCIARIA POPULAR S.A. | W50: =+MONTH(J50) -> 2 | X50: =+ VLOOKUP(W50,'COMISIONES ENERO-MARZO 2025 (2)'!X:Y,2,0) -> Febrero
A51: 5502 - COMISIONES | B51: 53051501 | C51: BANCOS COMISIONES | D51: 0 | E51: 7426250 | F51: -7426250 | J51: 45707 | K51: NIC-00036228 | L51: DEVOLUCION DE DSF - GASTOS BANCARIOS MES DE ENERO 2025 | M51: DEVOLUCION DE DSF - GASTOS BANCARIOS MES DE ENERO 2025 | N51: 891900196 | O51: INGENIO CARMELITA S.A. | P51: 800182281 | Q51: FIDUCIARIA DAVIVIENDA S.A | W51: =+MONTH(J51) -> 2 | X51: =+ VLOOKUP(W51,'COMISIONES ENERO-MARZO 2025 (2)'!X:Y,2,0) -> Febrero
A52: 5502 - COMISIONES | B52: 53051501 | C52: BANCOS COMISIONES | D52: 0 | E52: 4303049 | F52: -4303049 | J52: 45707 | K52: NIC-00036228 | L52: DEVOLUCION DE DSF - GASTOS BANCARIOS MES DE ENERO 2025 | M52: DEVOLUCION DE DSF - GASTOS BANCARIOS MES DE ENERO 2025 | N52: 891900196 | O52: INGENIO CARMELITA S.A. | P52: 860002964 | Q52: BANCO DE BOGOTA | W52: =+MONTH(J52) -> 2 | X52: =+ VLOOKUP(W52,'COMISIONES ENERO-MARZO 2025 (2)'!X:Y,2,0) -> Febrero
A53: 5502 - COMISIONES | B53: 53051501 | C53: BANCOS COMISIONES | D53: 0 | E53: 43927682 | F53: -43927682 | J53: 45707 | K53: NIC-00036228 | L53: DEVOLUCION DE DSF - GASTOS BANCARIOS MES DE ENERO 2025 | M53: DEVOLUCION DE DSF - GASTOS BANCARIOS MES DE ENERO 2025 | N53: 891900196 | O53: INGENIO CARMELITA S.A. | P53: 860003020 | Q53: BBVA COLOMBIA S.A. | W53: =+MONTH(J53) -> 2 | X53: =+ VLOOKUP(W53,'COMISIONES ENERO-MARZO 2025 (2)'!X:Y,2,0) -> Febrero
A54: 5502 - COMISIONES | B54: 53051501 | C54: BANCOS COMISIONES | D54: 0 | E54: 2650 | F54: -2650 | J54: 45707 | K54: NIC-00036228 | L54: DEVOLUCION DE DSF - GASTOS BANCARIOS MES DE ENERO 2025 | M54: DEVOLUCION DE DSF - GASTOS BANCARIOS MES DE ENERO 2025 | N54: 891900196 | O54: INGENIO CARMELITA S.A. | P54: 860007738 | Q54: BANCO POPULAR | W54: =+MONTH(J54) -> 2 | X54: =+ VLOOKUP(W54,'COMISIONES ENERO-MARZO 2025 (2)'!X:Y,2,0) -> Febrero
A55: 5502 - COMISIONES | B55: 53051501 | C55: BANCOS COMISIONES | D55: 0 | E55: 9801719 | F55: -9801719 | J55: 45707 | K55: NIC-00036228 | L55: DEVOLUCION DE DSF - GASTOS BANCARIOS MES DE ENERO 2025 | M55: DEVOLUCION DE DSF - GASTOS BANCARIOS MES DE ENERO 2025 | N55: 891900196 | O55: INGENIO CARMELITA S.A. | P55: 860034313 | Q55: DAVIVIENDA | W55: =+MONTH(J55) -> 2 | X55: =+ VLOOKUP(W55,'COMISIONES ENERO-MARZO 2025 (2)'!X:Y,2,0) -> Febrero
A56: 5502 - COMISIONES | B56: 53051501 | C56: BANCOS COMISIONES | D56: 0 | E56: 4739977 | F56: -4739977 | J56: 45707 | K56: NIC-00036228 | L56: DEVOLUCION DE DSF - GASTOS BANCARIOS MES DE ENERO 2025 | M56: DEVOLUCION DE DSF - GASTOS BANCARIOS MES DE ENERO 2025 | N56: 891900196 | O56: INGENIO CARMELITA S.A. | P56: 890903938 | Q56: BANCOLOMBIA | W56: =+MONTH(J56) -> 2 | X56: =+ VLOOKUP(W56,'COMISIONES ENERO-MARZO 2025 (2)'!X:Y,2,0) -> Febrero
A57: 5502 - COMISIONES | B57: 53051501 | C57: BANCOS COMISIONES | D57: 0 | E57: 514829.43 | F57: -514829.43 | J57: 45707 | K57: NIC-00036228 | L57: DEVOLUCION DE DSF - GASTOS BANCARIOS MES DE ENERO 2025 | M57: DEVOLUCION DE DSF - GASTOS BANCARIOS MES DE ENERO 2025 | N57: 891900196 | O57: INGENIO CARMELITA S.A. | P57: 928149105971DV28 | Q57: BANCOLOMBIA PANAMA | W57: =+MONTH(J57) -> 2 | X57: =+ VLOOKUP(W57,'COMISIONES ENERO-MARZO 2025 (2)'!X:Y,2,0) -> Febrero
A58: 5502 - COMISIONES | B58: 53051501 | C58: BANCOS COMISIONES | D58: 1792877.1 | E58: 0 | F58: 1792877.1 | J58: 45713 | K58: NIB-00006062 | L58: FACTORING BBVA FAN-29239 COMISIONES | M58: FACTORING BBVA FAN-29239 COMISIONES | N58: 890800718 | O58: CASA LUKER SA | P58: 860003020 | Q58: BBVA COLOMBIA S.A. | W58: =+MONTH(J58) -> 2 | X58: =+ VLOOKUP(W58,'COMISIONES ENERO-MARZO 2025 (2)'!X:Y,2,0) -> Febrero
A59: 5502 - COMISIONES | B59: 53051501 | C59: BANCOS COMISIONES | D59: 3529 | E59: 0 | F59: 3529 | J59: 45713 | K59: NIP-00016767 | L59: CONTABILIZACIÓN IVA COMISON 4*1000 | M59: CONTABILIZACIÓN IVA COMISON 4*1000 | N59: 16502466 | O59: SANTACRUZ JOHN | P59: 890903938 | Q59: BANCOLOMBIA | W59: =+MONTH(J59) -> 2 | X59: =+ VLOOKUP(W59,'COMISIONES ENERO-MARZO 2025 (2)'!X:Y,2,0) -> Febrero
A60: 5502 - COMISIONES | B60: 53051501 | C60: BANCOS COMISIONES | D60: 9251104.8 | E60: 0 | F60: 9251104.8 | J60: 45715 | K60: NIB-00006091 | L60: FACTORING BBVA-COMISIONES FAN-29218-251-256-288-309-324 | M60: FACTORING BBVA-COMISIONES FAN-29218-251-256-288-309-324 | N60: 890805267 | O60: SUPER DE ALIMENTOS S.A.S. | P60: 860003020 | Q60: BBVA COLOMBIA S.A. | W60: =+MONTH(J60) -> 2 | X60: =+ VLOOKUP(W60,'COMISIONES ENERO-MARZO 2025 (2)'!X:Y,2,0) -> Febrero
A61: 5502 - COMISIONES | B61: 53051501 | C61: BANCOS COMISIONES | D61: 1162707.3 | E61: 0 | F61: 1162707.3 | J61: 45715 | K61: NIB-00006098 | L61: FACTORING BBVA FAN-29038 REGISTRO COMISION | M61: FACTORING BBVA FAN-29038 REGISTRO COMISION | N61: 900079775 | O61: GOLOSINAS TRULULU S.A. | P61: 860003020 | Q61: BBVA COLOMBIA S.A. | W61: =+MONTH(J61) -> 2 | X61: =+ VLOOKUP(W61,'COMISIONES ENERO-MARZO 2025 (2)'!X:Y,2,0) -> Febrero
A62: 5502 - COMISIONES | B62: 53051501 | C62: BANCOS COMISIONES | D62: 11424.49 | E62: 0 | F62: 11424.49 | J62: 45715 | K62: NIC-00036273 | L62: Ajuste de tercero en NIB5875 - Pago de facturas a nombre de INGENIERIA Y EQUIPOS PARA LA INDUSTRIA - INGEPIN | M62: Ajuste de tercero en NIB5875 - Pago de facturas a nombre de INGENIERIA Y EQUIPOS PARA LA INDUSTRIA - INGEPIN | N62: 891900196 | O62: INGENIO CARMELITA S.A. | P62: 800037800 | Q62: BANCO AGRARIO DE COLOMBIA S.A | W62: =+MONTH(J62) -> 2 | X62: =+ VLOOKUP(W62,'COMISIONES ENERO-MARZO 2025 (2)'!X:Y,2,0) -> Febrero
A63: 5502 - COMISIONES | B63: 53051501 | C63: BANCOS COMISIONES | D63: 0 | E63: 11424.49 | F63: -11424.49 | J63: 45715 | K63: NIC-00036273 | L63: Ajuste de tercero en NIB5875 - Pago de facturas a nombre de INGENIERIA Y EQUIPOS PARA LA INDUSTRIA - INGEPIN | M63: Ajuste de tercero en NIB5875 - Pago de facturas a nombre de INGENIERIA Y EQUIPOS PARA LA INDUSTRIA - INGEPIN | N63: 891900196 | O63: INGENIO CARMELITA S.A. | P63: 890903938 | Q63: BANCOLOMBIA | W63: =+MONTH(J63) -> 2 | X63: =+ VLOOKUP(W63,'COMISIONES ENERO-MARZO 2025 (2)'!X:Y,2,0) -> Febrero
A64: 5502 - COMISIONES | B64: 53051501 | C64: BANCOS COMISIONES | D64: 239997.6 | E64: 0 | F64: 239997.6 | J64: 45715 | K64: NIC-00036277 | L64: GASTO COMISION MES DE ENERO 2025 BANCO ITAU | M64: Registro de partidas conciliadas en Conciliación Bancaria correspondiente al mes de Enero 2025 | N64: 891900196 | O64: INGENIO CARMELITA S.A. | P64: 890903937 | Q64: ITAU CORPBANCA COLOMBIA SA | W64: =+MONTH(J64) -> 2 | X64: =+ VLOOKUP(W64,'COMISIONES ENERO-MARZO 2025 (2)'!X:Y,2,0) -> Febrero
A65: 5502 - COMISIONES | B65: 53051501 | C65: BANCOS COMISIONES | D65: 3558750 | E65: 0 | F65: 3558750 | J65: 45716 | K65: FAC-00045545 | L65: SOC82093 - D1- COMISION POR ADMINISTRACION, PERIODO DE FACTRUACION: FEBRERO 2025 | M65: SOC82093 - D1- COMISION POR ADMINISTRACION, PERIODO DE FACTRUACION: FEBRERO 2025 | N65: 800182281 | O65: FIDUCIARIA DAVIVIENDA S.A | P65: 800182281 | Q65: FIDUCIARIA DAVIVIENDA S.A | W65: =+MONTH(J65) -> 2 | X65: =+ VLOOKUP(W65,'COMISIONES ENERO-MARZO 2025 (2)'!X:Y,2,0) -> Febrero
A66: 5502 - COMISIONES | B66: 53051501 | C66: BANCOS COMISIONES | D66: 3558750 | E66: 0 | F66: 3558750 | J66: 45716 | K66: FAC-00045546 | L66: FAC133255 - COMISION FIDUCIARIA MES DE FEBRERO 2025- COMISION FIJA 2.5 SMMLV | M66: FAC133255 - COMISION FIDUCIARIA MES DE FEBRERO 2025- COMISION FIJA 2.5 SMMLV | N66: 800141235 | O66: FIDUCIARIA POPULAR S.A. | P66: 800141235 | Q66: FIDUCIARIA POPULAR S.A. | W66: =+MONTH(J66) -> 2 | X66: =+ VLOOKUP(W66,'COMISIONES ENERO-MARZO 2025 (2)'!X:Y,2,0) -> Febrero
A67: 5502 - COMISIONES | B67: 53051501 | C67: BANCOS COMISIONES | D67: 16300 | E67: 0 | F67: 16300 | J67: 45716 | K67: NIB-00006094 | L67: GASTOS BANCARIOS - BANCO BOGOTA CALI CTE 256096355 - MES DE ENERO 2025 | M67: GASTOS BANCARIOS - BANCO BOGOTA CALI CTE 256096355 - MES DE ENERO 2025 | N67: 860002964 | O67: BANCO DE BOGOTA | P67: 860002964 | Q67: BANCO DE BOGOTA | W67: =+MONTH(J67) -> 2 | X67: =+ VLOOKUP(W67,'COMISIONES ENERO-MARZO 2025 (2)'!X:Y,2,0) -> Febrero
A68: 5502 - COMISIONES | B68: 53051501 | C68: BANCOS COMISIONES | D68: 284369.99 | E68: 0 | F68: 284369.99 | J68: 45716 | K68: NIB-00006100 | L68: GATOS BANCARIOS Y RENIDMIENTOS FINANCIEROS, MES DE FEBRERO 2025 - BANCOLOMBIA PANAMA | M68: GATOS BANCARIOS Y RENIDMIENTOS FINANCIEROS, MES DE FEBRERO 2025 - BANCOLOMBIA PANAMA | N68: 928149105971DV28 | O68: BANCOLOMBIA PANAMA | P68: 928149105971DV28 | Q68: BANCOLOMBIA PANAMA | W68: =+MONTH(J68) -> 2 | X68: =+ VLOOKUP(W68,'COMISIONES ENERO-MARZO 2025 (2)'!X:Y,2,0) -> Febrero
A69: 5502 - COMISIONES | B69: 53051501 | C69: BANCOS COMISIONES | D69: 4199416.6 | E69: 0 | F69: 4199416.6 | J69: 45716 | K69: NIB-00006131 | L69: GASTOS BANCARIOS MES DE FEBRERO 2025 - BANCOLOMBIA CTE 80104152201 | M69: GASTOS BANCARIOS MES DE FEBRERO 2025 - BANCOLOMBIA CTE 80104152201 | N69: 890903938 | O69: BANCOLOMBIA | P69: 890903938 | Q69: BANCOLOMBIA | W69: =+MONTH(J69) -> 2 | X69: =+ VLOOKUP(W69,'COMISIONES ENERO-MARZO 2025 (2)'!X:Y,2,0) -> Febrero
A70: 5502 - COMISIONES | B70: 53051501 | C70: BANCOS COMISIONES | D70: 1604625 | E70: 0 | F70: 1604625 | J70: 45716 | K70: NIB-00006159 | L70: GASTOS BANCARIOS MES DE FEBRERO 2025 - BANCO DE BOGOTA TULUA CTE 612036319 | M70: GASTOS BANCARIOS MES DE FEBRERO 2025 - BANCO DE BOGOTA TULUA CTE 612036319 | N70: 860002964 | O70: BANCO DE BOGOTA | P70: 860002964 | Q70: BANCO DE BOGOTA | W70: =+MONTH(J70) -> 2 | X70: =+ VLOOKUP(W70,'COMISIONES ENERO-MARZO 2025 (2)'!X:Y,2,0) -> Febrero
A71: 5502 - COMISIONES | B71: 53051501 | C71: BANCOS COMISIONES | D71: 54140 | E71: 0 | F71: 54140 | J71: 45716 | K71: NIB-00006160 | L71: Comision por generacion de extractos bancarios , Interes ´por sobregiro en extracto Febero 2025 | M71: Comision por generacion de extractos bancarios , Interes ´por sobregiro en extracto Febero 2025 | N71: 860002964 | O71: BANCO DE BOGOTA | P71: 860002964 | Q71: BANCO DE BOGOTA | W71: =+MONTH(J71) -> 2 | X71: =+ VLOOKUP(W71,'COMISIONES ENERO-MARZO 2025 (2)'!X:Y,2,0) -> Febrero
A72: 5502 - COMISIONES | B72: 53051501 | C72: BANCOS COMISIONES | D72: 8162148 | E72: 0 | F72: 8162148 | J72: 45716 | K72: NIB-00006164 | L72: GASTOS BANCARIOS MES DE FEBRERO 2025 - BANCO DAVIVIENDA CTE 379469997678 | M72: GASTOS BANCARIOS MES DE FEBRERO 2025 - BANCO DAVIVIENDA CTE 379469997678 | N72: 860034313 | O72: DAVIVIENDA | P72: 860034313 | Q72: DAVIVIENDA | W72: =+MONTH(J72) -> 2 | X72: =+ VLOOKUP(W72,'COMISIONES ENERO-MARZO 2025 (2)'!X:Y,2,0) -> Febrero
A73: 5502 - COMISIONES | B73: 53051501 | C73: BANCOS COMISIONES | D73: 0 | E73: 639375 | F73: -639375 | J73: 45716 | K73: NIC-00036462 | L73: RECLASIFICACION FAN-27800 A FAN - 27746 | M73: RECLASIFICACION FAN-27800 A FAN - 27746 | N73: 900079775 | O73: GOLOSINAS TRULULU S.A. | P73: 860003020 | Q73: BBVA COLOMBIA S.A. | W73: =+MONTH(J73) -> 2 | X73: =+ VLOOKUP(W73,'COMISIONES ENERO-MARZO 2025 (2)'!X:Y,2,0) -> Febrero
A74: 5502 - COMISIONES | B74: 53051501 | C74: BANCOS COMISIONES | D74: 37562146 | E74: 0 | F74: 37562146 | J74: 45716 | K74: NIC-00036474 | L74: RECLASIFICACION 529505 A 530515 COMISIONES BBVA - KLYM FEB 2025 | M74: RECLASIFICACION 529505 A 530515 COMISIONES BBVA - KLYM FEB 2025 | N74: 891900196 | O74: INGENIO CARMELITA S.A. | P74: 860003020 | Q74: BBVA COLOMBIA S.A. | W74: =+MONTH(J74) -> 2 | X74: =+ VLOOKUP(W74,'COMISIONES ENERO-MARZO 2025 (2)'!X:Y,2,0) -> Febrero
A75: 5502 - COMISIONES | B75: 53051501 | C75: BANCOS COMISIONES | D75: 3496088 | E75: 0 | F75: 3496088 | J75: 45716 | K75: NIC-00036474 | L75: RECLASIFICACION 529505 A 530515 COMISIONES BBVA - KLYM FEB 2025 | M75: RECLASIFICACION 529505 A 530515 COMISIONES BBVA - KLYM FEB 2025 | N75: 891900196 | O75: INGENIO CARMELITA S.A. | P75: 900296536 | Q75: KLYM S.A.S | W75: =+MONTH(J75) -> 2 | X75: =+ VLOOKUP(W75,'COMISIONES ENERO-MARZO 2025 (2)'!X:Y,2,0) -> Febrero
A76: 5502 - COMISIONES | B76: 53051501 | C76: BANCOS COMISIONES | D76: 2230352.2 | E76: 0 | F76: 2230352.2 | J76: 45716 | K76: NIC-00036475 | L76: RECLASIFICION COMISIONES TRULULU FEB 2025 5295 A 5305 | M76: RECLASIFICION COMISIONES TRULULU FEB 2025 5295 A 5305 | N76: 860003020 | O76: BBVA COLOMBIA S.A. | P76: 860003020 | Q76: BBVA COLOMBIA S.A. | W76: =+MONTH(J76) -> 2 | X76: =+ VLOOKUP(W76,'COMISIONES ENERO-MARZO 2025 (2)'!X:Y,2,0) -> Febrero
A77: 5502 - COMISIONES | B77: 53051501 | C77: BANCOS COMISIONES | D77: 5112511 | E77: 0 | F77: 5112511 | J77: 45716 | K77: NIP-00016803 | L77: CLFV21037 - COMISIONES - SERV DE REGISTRO BMN 8600071250 - IVA SRRV REGISTRADO BMC 19% | M77: CLFV21037 - COMISIONES - SERV DE REGISTRO BMN 8600071250 - IVA SRRV REGISTRADO BMC 19% | N77: 805000867 | O77: CORREAGRO S.A. | P77: 805000867 | Q77: CORREAGRO S.A. | W77: =+MONTH(J77) -> 2 | X77: =+ VLOOKUP(W77,'COMISIONES ENERO-MARZO 2025 (2)'!X:Y,2,0) -> Febrero
A78: 5502 - COMISIONES | B78: 53051501 | C78: BANCOS COMISIONES | D78: 17909491 | E78: 0 | F78: 17909491 | J78: 45716 | K78: NIP-00016804 | L78: CLFV21038- COMISIONES - SERV DE REGISTRO BMN 8600071250 - IVA SRRV REGISTRADO BMC 19% | M78: CLFV21038- COMISIONES - SERV DE REGISTRO BMN 8600071250 - IVA SRRV REGISTRADO BMC 19% | N78: 805000867 | O78: CORREAGRO S.A. | P78: 805000867 | Q78: CORREAGRO S.A. | W78: =+MONTH(J78) -> 2 | X78: =+ VLOOKUP(W78,'COMISIONES ENERO-MARZO 2025 (2)'!X:Y,2,0) -> Febrero
A79: 5502 - COMISIONES | B79: 53051501 | C79: BANCOS COMISIONES | D79: 3529 | E79: 0 | F79: 3529 | J79: 45720 | K79: NIP-00016805 | L79: CONTABILIZACIÓN IVA COMISION 4*1000 | M79: CONTABILIZACIÓN IVA COMISION 4*1000 | N79: 1144185697 | O79: REYES MORIONES ANGELICA | P79: 890903938 | Q79: BANCOLOMBIA | W79: =+MONTH(J79) -> 3 | X79: =+ VLOOKUP(W79,'COMISIONES ENERO-MARZO 2025 (2)'!X:Y,2,0) -> Marzo
A80: 5502 - COMISIONES | B80: 53051501 | C80: BANCOS COMISIONES | D80: 3529 | E80: 0 | F80: 3529 | J80: 45720 | K80: NIP-00016806 | L80: CONTABILIZACION IVA COMISION 4*1000 | M80: CONTABILIZACION IVA COMISION 4*1000 | N80: 16502466 | O80: SANTACRUZ JOHN | P80: 890903938 | Q80: BANCOLOMBIA | W80: =+MONTH(J80) -> 3 | X80: =+ VLOOKUP(W80,'COMISIONES ENERO-MARZO 2025 (2)'!X:Y,2,0) -> Marzo
... A91: 5502 - COMISIONES | B91: 53051501 | C91: BANCOS COMISIONES | D91: 1423500 | E91: 0 | F91: 1423500 | J91: 45736 | K91: FAC-00045724 | L91: FAC992663 - COMISION FIJA DE ADMINISTRACION CORRESPONDIENTE AL MES DE MARZO 2025 | M91: FAC992663 - COMISION FIJA DE ADMINISTRACION CORRESPONDIENTE AL MES DE MARZO 2025 | N91: 860531315 | O91: ALIANZA FIDUCIARIA S.A | P91: 860531315 | Q91: ALIANZA FIDUCIARIA S.A | W91: =+MONTH(J91) -> 3 | X91: =+ VLOOKUP(W91,'COMISIONES ENERO-MARZO 2025 (2)'!X:Y,2,0) -> Marzo
A92: 5502 - COMISIONES | B92: 53051501 | C92: BANCOS COMISIONES | D92: 1675065 | E92: 0 | F92: 1675065 | J92: 45737 | K92: DSF-00001104 | L92: GASTOS BANCARIOS CORRESPONDIENTES AL MES DE FEBRERO 2025 | M92: GASTOS BANCARIOS CORRESPONDIENTES AL MES DE FEBRERO 2025 | N92: 860002964 | O92: BANCO DE BOGOTA | P92: 860002964 | Q92: BANCO DE BOGOTA | V92: DSF | W92: =+MONTH(J92) -> 3 | X92: =+ VLOOKUP(W92,'COMISIONES ENERO-MARZO 2025 (2)'!X:Y,2,0) -> Marzo
A93: 5502 - COMISIONES | B93: 53051501 | C93: BANCOS COMISIONES | D93: 4209166.2 | E93: 0 | F93: 4209166.2 | J93: 45737 | K93: DSF-00001106 | L93: GASTOS BANCARIOS CORRESPONDIENTES AL MES DE FEBRERO 2025 | M93: GASTOS BANCARIOS CORRESPONDIENTES AL MES DE FEBRERO 2025 | N93: 890903938 | O93: BANCOLOMBIA | P93: 890903938 | Q93: BANCOLOMBIA | V93: DSF | W93: =+MONTH(J93) -> 3 | X93: =+ VLOOKUP(W93,'COMISIONES ENERO-MARZO 2025 (2)'!X:Y,2,0) -> Marzo
A94: 5502 - COMISIONES | B94: 53051501 | C94: BANCOS COMISIONES | D94: 8162148 | E94: 0 | F94: 8162148 | J94: 45737 | K94: DSF-00001107 | L94: GASTOS BANCARIOS CORRESPONDIENTES AL MES DE FEBRERO 2025 - INCLUYE INT. COGENERACION | M94: GASTOS BANCARIOS CORRESPONDIENTES AL MES DE FEBRERO 2025 - INCLUYE INT. COGENERACION | N94: 860034313 | O94: DAVIVIENDA | P94: 860034313 | Q94: DAVIVIENDA | V94: DSF | W94: =+MONTH(J94) -> 3 | X94: =+ VLOOKUP(W94,'COMISIONES ENERO-MARZO 2025 (2)'!X:Y,2,0) -> Marzo
A95: 5502 - COMISIONES | B95: 53051501 | C95: BANCOS COMISIONES | D95: 32028.49 | E95: 0 | F95: 32028.49 | J95: 45737 | K95: DSF-00001108 | L95: GASTOS BANCARIOS CORRESPONDIENTES AL MES DE FEBRERO 2025 | M95: GASTOS BANCARIOS CORRESPONDIENTES AL MES DE FEBRERO 2025 | N95: 800037800 | O95: BANCO AGRARIO DE COLOMBIA S.A | P95: 800037800 | Q95: BANCO AGRARIO DE COLOMBIA S.A | V95: DSF | W95: =+MONTH(J95) -> 3 | X95: =+ VLOOKUP(W95,'COMISIONES ENERO-MARZO 2025 (2)'!X:Y,2,0) -> Marzo
A96: 5502 - COMISIONES | B96: 53051501 | C96: BANCOS COMISIONES | D96: 51359812 | E96: 0 | F96: 51359812 | J96: 45737 | K96: DSF-00001111 | L96: GASTOS BANCARIOS CORRESPONDIENTES AL MES DE FEBRERO 2025 | M96: GASTOS BANCARIOS CORRESPONDIENTES AL MES DE FEBRERO 2025 | N96: 860003020 | O96: BBVA COLOMBIA S.A. | P96: 860003020 | Q96: BBVA COLOMBIA S.A. | V96: DSF | W96: =+MONTH(J96) -> 3 | X96: =+ VLOOKUP(W96,'COMISIONES ENERO-MARZO 2025 (2)'!X:Y,2,0) -> Marzo
A97: 5502 - COMISIONES | B97: 53051501 | C97: BANCOS COMISIONES | D97: 3558750 | E97: 0 | F97: 3558750 | J97: 45737 | K97: DSF-00001112 | L97: GASTOS BANCARIOS CORRESPONDIENTES AL MES DE FEBRERO 2025 | M97: GASTOS BANCARIOS CORRESPONDIENTES AL MES DE FEBRERO 2025 | N97: 800141235 | O97: FIDUCIARIA POPULAR S.A. | P97: 800141235 | Q97: FIDUCIARIA POPULAR S.A. | V97: DSF | W97: =+MONTH(J97) -> 3 | X97: =+ VLOOKUP(W97,'COMISIONES ENERO-MARZO 2025 (2)'!X:Y,2,0) -> Marzo
A98: 5502 - COMISIONES | B98: 53051501 | C98: BANCOS COMISIONES | D98: 3558750 | E98: 0 | F98: 3558750 | J98: 45737 | K98: DSF-00001113 | L98: GASTOS BANCARIOS CORRESPONDIENTES AL MES DE FEBRERO 2025 | M98: GASTOS BANCARIOS CORRESPONDIENTES AL MES DE FEBRERO 2025 | N98: 800182281 | O98: FIDUCIARIA DAVIVIENDA S.A | P98: 800182281 | Q98: FIDUCIARIA DAVIVIENDA S.A | V98: DSF | W98: =+MONTH(J98) -> 3 | X98: =+ VLOOKUP(W98,'COMISIONES ENERO-MARZO 2025 (2)'!X:Y,2,0) -> Marzo
A99: 5502 - COMISIONES | B99: 53051501 | C99: BANCOS COMISIONES | D99: 284369.99 | E99: 0 | F99: 284369.99 | J99: 45737 | K99: DSF-00001114 | L99: GASTOS BANCARIOS CORRESPONDIENTES AL MES DE FEBRERO 2025 | M99: GASTOS BANCARIOS CORRESPONDIENTES AL MES DE FEBRERO 2025 | N99: 928149105971DV28 | O99: BANCOLOMBIA PANAMA | P99: 928149105971DV28 | Q99: BANCOLOMBIA PANAMA | V99: DSF | W99: =+MONTH(J99) -> 3 | X99: =+ VLOOKUP(W99,'COMISIONES ENERO-MARZO 2025 (2)'!X:Y,2,0) -> Marzo
A100: 5502 - COMISIONES | B100: 53051501 | C100: BANCOS COMISIONES | D100: 1809003 | E100: 0 | F100: 1809003 | J100: 45737 | K100: NIB-00006305 | L100: FACTORING BBVA FAN-29561 COMISION | M100: FACTORING BBVA FAN-29561 COMISION | N100: 890805267 | O100: SUPER DE ALIMENTOS S.A.S. | P100: 860003020 | Q100: BBVA COLOMBIA S.A. | W100: =+MONTH(J100) -> 3 | X100: =+ VLOOKUP(W100,'COMISIONES ENERO-MARZO 2025 (2)'!X:Y,2,0) -> Marzo
A101: 5502 - COMISIONES | B101: 53051501 | C101: BANCOS COMISIONES | D101: 12271970 | E101: 0 | F101: 12271970 | J101: 45737 | K101: NIB-00006382 | L101: FACTORIN BBVA-29557-584-589-599-600-612-634-650 COMISION | M101: FACTORING BBVA-29557-584-589-599-600-612-634-650 COMISION | N101: 890805267 | O101: SUPER DE ALIMENTOS S.A.S. | P101: 860003020 | Q101: BBVA COLOMBIA S.A. | W101: =+MONTH(J101) -> 3 | X101: =+ VLOOKUP(W101,'COMISIONES ENERO-MARZO 2025 (2)'!X:Y,2,0) -> Marzo
A102: 5502 - COMISIONES | B102: 53051501 | C102: BANCOS COMISIONES | D102: 153140 | E102: 0 | F102: 153140 | J102: 45737 | K102: NIC-00036581 | L102: Cobro comision por Generacion de extracto bancario- 256096355 BGTA CALI | M102: REGISTRO DE PARTIDAS CONCILIADAS EN CONCILIACION BANCARIA MES DE FEBRERO 2025 | N102: 891900196 | O102: INGENIO CARMELITA S.A. | P102: 860002964 | Q102: BANCO DE BOGOTA | W102: =+MONTH(J102) -> 3 | X102: =+ VLOOKUP(W102,'COMISIONES ENERO-MARZO 2025 (2)'!X:Y,2,0) -> Marzo
A103: 5502 - COMISIONES | B103: 53051501 | C103: BANCOS COMISIONES | D103: 239997.6 | E103: 0 | F103: 239997.6 | J103: 45737 | K103: NIC-00036581 | L103: COMISION BANCARIA CTA CTE 301-44051-7 BACO ITAU | M103: REGISTRO DE PARTIDAS CONCILIADAS EN CONCILIACION BANCARIA MES DE FEBRERO 2025 | N103: 891900196 | O103: INGENIO CARMELITA S.A. | P103: 890903937 | Q103: ITAU CORPBANCA COLOMBIA SA | W103: =+MONTH(J103) -> 3 | X103: =+ VLOOKUP(W103,'COMISIONES ENERO-MARZO 2025 (2)'!X:Y,2,0) -> Marzo
A104: 5502 - COMISIONES | B104: 53051501 | C104: BANCOS COMISIONES | D104: 9020.32 | E104: 0 | F104: 9020.32 | J104: 45737 | K104: NIC-00036581 | L104: DEBITO POR RECHAZOS- BANCOLOMBIA CTA CTE 80104152201 | M104: REGISTRO DE PARTIDAS CONCILIADAS EN CONCILIACION BANCARIA MES DE FEBRERO 2025 | N104: 891900196 | O104: INGENIO CARMELITA S.A. | P104: 890903938 | Q104: BANCOLOMBIA | W104: =+MONTH(J104) -> 3 | X104: =+ VLOOKUP(W104,'COMISIONES ENERO-MARZO 2025 (2)'!X:Y,2,0) -> Marzo
A105: 5502 - COMISIONES | B105: 53051501 | C105: BANCOS COMISIONES | D105: 0 | E105: 32028.49 | F105: -32028.49 | J105: 45737 | K105: NIC-00036582 | L105: DEVOLUCION DE DSF - GASTOS BANCARIOS MES DE FEBRERO 2025 (DSF1104 AL 1114) | M105: DEVOLUCION DE DSF - GASTOS BANCARIOS MES DE FEBRERO 2025 (DSF1104 AL 1114) | N105: 891900196 | O105: INGENIO CARMELITA S.A. | P105: 800037800 | Q105: BANCO AGRARIO DE COLOMBIA S.A | W105: =+MONTH(J105) -> 3 | X105: =+ VLOOKUP(W105,'COMISIONES ENERO-MARZO 2025 (2)'!X:Y,2,0) -> Marzo
A106: 5502 - COMISIONES | B106: 53051501 | C106: BANCOS COMISIONES | D106: 0 | E106: 3558750 | F106: -3558750 | J106: 45737 | K106: NIC-00036582 | L106: DEVOLUCION DE DSF - GASTOS BANCARIOS MES DE FEBRERO 2025 (DSF1104 AL 1114) | M106: DEVOLUCION DE DSF - GASTOS BANCARIOS MES DE FEBRERO 2025 (DSF1104 AL 1114) | N106: 891900196 | O106: INGENIO CARMELITA S.A. | P106: 800141235 | Q106: FIDUCIARIA POPULAR S.A. | W106: =+MONTH(J106) -> 3 | X106: =+ VLOOKUP(W106,'COMISIONES ENERO-MARZO 2025 (2)'!X:Y,2,0) -> Marzo
A107: 5502 - COMISIONES | B107: 53051501 | C107: BANCOS COMISIONES | D107: 0 | E107: 3558750 | F107: -3558750 | J107: 45737 | K107: NIC-00036582 | L107: DEVOLUCION DE DSF - GASTOS BANCARIOS MES DE FEBRERO 2025 (DSF1104 AL 1114) | M107: DEVOLUCION DE DSF - GASTOS BANCARIOS MES DE FEBRERO 2025 (DSF1104 AL 1114) | N107: 891900196 | O107: INGENIO CARMELITA S.A. | P107: 800182281 | Q107: FIDUCIARIA DAVIVIENDA S.A | W107: =+MONTH(J107) -> 3 | X107: =+ VLOOKUP(W107,'COMISIONES ENERO-MARZO 2025 (2)'!X:Y,2,0) -> Marzo
A108: 5502 - COMISIONES | B108: 53051501 | C108: BANCOS COMISIONES | D108: 0 | E108: 1675065 | F108: -1675065 | J108: 45737 | K108: NIC-00036582 | L108: DEVOLUCION DE DSF - GASTOS BANCARIOS MES DE FEBRERO 2025 (DSF1104 AL 1114) | M108: DEVOLUCION DE DSF - GASTOS BANCARIOS MES DE FEBRERO 2025 (DSF1104 AL 1114) | N108: 891900196 | O108: INGENIO CARMELITA S.A. | P108: 860002964 | Q108: BANCO DE BOGOTA | W108: =+MONTH(J108) -> 3 | X108: =+ VLOOKUP(W108,'COMISIONES ENERO-MARZO 2025 (2)'!X:Y,2,0) -> Marzo
A109: 5502 - COMISIONES | B109: 53051501 | C109: BANCOS COMISIONES | D109: 0 | E109: 51359812 | F109: -51359812 | J109: 45737 | K109: NIC-00036582 | L109: DEVOLUCION DE DSF - GASTOS BANCARIOS MES DE FEBRERO 2025 (DSF1104 AL 1114) | M109: DEVOLUCION DE DSF - GASTOS BANCARIOS MES DE FEBRERO 2025 (DSF1104 AL 1114) | N109: 891900196 | O109: INGENIO CARMELITA S.A. | P109: 860003020 | Q109: BBVA COLOMBIA S.A. | W109: =+MONTH(J109) -> 3 | X109: =+ VLOOKUP(W109,'COMISIONES ENERO-MARZO 2025 (2)'!X:Y,2,0) -> Marzo
A110: 5502 - COMISIONES | B110: 53051501 | C110: BANCOS COMISIONES | D110: 0 | E110: 8162148 | F110: -8162148 | J110: 45737 | K110: NIC-00036582 | L110: DEVOLUCION DE DSF - GASTOS BANCARIOS MES DE FEBRERO 2025 (DSF1104 AL 1114) | M110: DEVOLUCION DE DSF - GASTOS BANCARIOS MES DE FEBRERO 2025 (DSF1104 AL 1114) | N110: 891900196 | O110: INGENIO CARMELITA S.A. | P110: 860034313 | Q110: DAVIVIENDA | W110: =+MONTH(J110) -> 3 | X110: =+ VLOOKUP(W110,'COMISIONES ENERO-MARZO 2025 (2)'!X:Y,2,0) -> Marzo
...

Sheet 4 x 1000
A1: C.Costo | B1: Desc. C.Costo | C1: CUENTA | D1: Auxiliar | E1: Desc. auxiliar | F1: Neto | G1: Docto. | H1: Fecha | I1: Notas | J1: Notas docto | K1: Razón social tercero movto. | L1: SECCION | M1: Prefijo tipo docto | N1: SUB SUBCUENTA | O1: Mes | P1: Año | Q1: Nombre Mes
C2: 5305 - DEL SECTOR FINANCIERO | D2: 53059501 | E2: IMPUESTO 4 X 1.000 | F2: =-1679385527.54*0 -> 0 | G2: CCR-00000049 | H2: 45657 | I2: CIERRE CONTABLE Y FISCAL AÑO 2024 | J2: CIERRE CONTABLE Y FISCAL AÑO 2024 | K2: Genérico | O2: =+MONTH(H2) -> 12 | P2: =+YEAR(H2) -> 2024 | Q2: =+VLOOKUP(O2,'COMISIONES ENERO-MARZO 2025 (2)'!$X:$Y,2,0) -> Diciembre
C3: 5305 - DEL SECTOR FINANCIERO | D3: 53059501 | E3: IMPUESTO 4 X 1.000 | F3: 260 | G3: MBC-00000325 | H3: 45322 | I3: GASTOS FINANCIEROS MES DE ENERO DE 2023 | J3: GASTOS FINANCIEROS MES DE ENERO DE 2023 | K3: BANCO DE BOGOTA | O3: =+MONTH(H3) -> 1 | P3: =+YEAR(H3) -> 2024 | Q3: =+VLOOKUP(O3,'COMISIONES ENERO-MARZO 2025 (2)'!$X:$Y,2,0) -> Enero
C4: 5305 - DEL SECTOR FINANCIERO | D4: 53059501 | E4: IMPUESTO 4 X 1.000 | F4: 36467595 | G4: MBC-00000326 | H4: 45322 | I4: GASTOS FINANCIEROS MES DE ENERO DE 2024 BOGOTA TULUA | J4: GASTOS FINANCIEROS MES DE ENERO DE 2024 BOGOTA TULUA | K4: BANCO DE BOGOTA | O4: =+MONTH(H4) -> 1 | P4: =+YEAR(H4) -> 2024 | Q4: =+VLOOKUP(O4,'COMISIONES ENERO-MARZO 2025 (2)'!$X:$Y,2,0) -> Enero
C5: 5305 - DEL SECTOR FINANCIERO | D5: 53059501 | E5: IMPUESTO 4 X 1.000 | F5: 40513274 | G5: MBC-00000327 | H5: 45322 | I5: GASTOS FINANCIEROS MES DE ENERO DE 2024 BANCOLOMBIA 801 | J5: GASTOS FINANCIEROS MES DE ENERO DE 2024 BANCOLOMBIA 801 | K5: BANCOLOMBIA | O5: =+MONTH(H5) -> 1 | P5: =+YEAR(H5) -> 2024 | Q5: =+VLOOKUP(O5,'COMISIONES ENERO-MARZO 2025 (2)'!$X:$Y,2,0) -> Enero
C6: 5305 - DEL SECTOR FINANCIERO | D6: 53059501 | E6: IMPUESTO 4 X 1.000 | F6: 63537748 | G6: MBC-00000328 | H6: 45351 | I6: GAST¿OS FINANCIEROS MES DE FEBRERO DE 2024 BANCOLOMBIA 801 | J6: GAST¿OS FINANCIEROS MES DE FEBRERO DE 2024 BANCOLOMBIA 801 | K6: BANCOLOMBIA | O6: =+MONTH(H6) -> 2 | P6: =+YEAR(H6) -> 2024 | Q6: =+VLOOKUP(O6,'COMISIONES ENERO-MARZO 2025 (2)'!$X:$Y,2,0) -> Febrero
C7: 5305 - DEL SECTOR FINANCIERO | D7: 53059501 | E7: IMPUESTO 4 X 1.000 | F7: 306 | G7: MBC-00000329 | H7: 45351 | I7: GASTOS FINANCIEROS MES DE FEBRERO DE 2024 BOGOTA CALI | J7: GASTOS FINANCIEROS MES DE FEBRERO DE 2024 BOGOTA CALI | K7: BANCO DE BOGOTA | O7: =+MONTH(H7) -> 2 | P7: =+YEAR(H7) -> 2024 | Q7: =+VLOOKUP(O7,'COMISIONES ENERO-MARZO 2025 (2)'!$X:$Y,2,0) -> Febrero
C8: 5305 - DEL SECTOR FINANCIERO | D8: 53059501 | E8: IMPUESTO 4 X 1.000 | F8: 32900855 | G8: MBC-00000330 | H8: 45351 | I8: GASTOS FINANCIEROS MES DE FEBRERO DE 2024- BOGOTA TULUA | J8: GASTOS FINANCIEROS MES DE FEBRERO DE 2024- BOGOTA TULUA | K8: BANCO DE BOGOTA | O8: =+MONTH(H8) -> 2 | P8: =+YEAR(H8) -> 2024 | Q8: =+VLOOKUP(O8,'COMISIONES ENERO-MARZO 2025 (2)'!$X:$Y,2,0) -> Febrero
C9: 5305 - DEL SECTOR FINANCIERO | D9: 53059501 | E9: IMPUESTO 4 X 1.000 | F9: 36889004 | G9: MBC-00000331 | H9: 45382 | I9: GASTOS FINANCIEROS MES DE MARZO DE 2024 | J9: GASTOS FINANCIEROS MES DE MARZO DE 2024 | K9: BANCOLOMBIA | O9: =+MONTH(H9) -> 3 | P9: =+YEAR(H9) -> 2024 | Q9: =+VLOOKUP(O9,'COMISIONES ENERO-MARZO 2025 (2)'!$X:$Y,2,0) -> Marzo
C10: 5305 - DEL SECTOR FINANCIERO | D10: 53059501 | E10: IMPUESTO 4 X 1.000 | F10: 10258 | G10: MBC-00000332 | H10: 45382 | I10: GASTOS FINANCIEROS MES DE MARZO BOGOTA CALIO | J10: GASTOS FINANCIEROS MES DE MARZO BOGOTA CALIO | K10: BANCO DE BOGOTA | O10: =+MONTH(H10) -> 3 | P10: =+YEAR(H10) -> 2024 | Q10: =+VLOOKUP(O10,'COMISIONES ENERO-MARZO 2025 (2)'!$X:$Y,2,0) -> Marzo
C11: 5305 - DEL SECTOR FINANCIERO | D11: 53059501 | E11: IMPUESTO 4 X 1.000 | F11: 34084348 | G11: MBC-00000333 | H11: 45382 | I11: GASTOS FINANCIEROS MES DE MARZO DE 2024 BOGOTA TULUA | J11: GASTOS FINANCIEROS MES DE MARZO DE 2024 BOGOTA TULUA | K11: BANCO DE BOGOTA | O11: =+MONTH(H11) -> 3 | P11: =+YEAR(H11) -> 2024 | Q11: =+VLOOKUP(O11,'COMISIONES ENERO-MARZO 2025 (2)'!$X:$Y,2,0) -> Marzo
C12: 5305 - DEL SECTOR FINANCIERO | D12: 53059501 | E12: IMPUESTO 4 X 1.000 | F12: 44302453 | G12: MBC-00000334 | H12: 45412 | I12: GASTOS FINANCIEROS MES DE ABRL 2024 - BANCOLOMBIA 801 | J12: GASTOS FINANCIEROS MES DE ABRL 2024 - BANCOLOMBIA 801 | K12: BANCOLOMBIA | O12: =+MONTH(H12) -> 4 | P12: =+YEAR(H12) -> 2024 | Q12: =+VLOOKUP(O12,'COMISIONES ENERO-MARZO 2025 (2)'!$X:$Y,2,0) -> Abril
C13: 5305 - DEL SECTOR FINANCIERO | D13: 53059501 | E13: IMPUESTO 4 X 1.000 | F13: 306 | G13: MBC-00000335 | H13: 45412 | I13: GASTOS FINANCIEROS MES DE ABRIL BOGOTA 256 | J13: GASTOS FINANCIEROS MES DE ABRIL BOGOTA 256 | K13: BANCO DE BOGOTA | O13: =+MONTH(H13) -> 4 | P13: =+YEAR(H13) -> 2024 | Q13: =+VLOOKUP(O13,'COMISIONES ENERO-MARZO 2025 (2)'!$X:$Y,2,0) -> Abril
C14: 5305 - DEL SECTOR FINANCIERO | D14: 53059501 | E14: IMPUESTO 4 X 1.000 | F14: 32381690 | G14: MBC-00000336 | H14: 45412 | I14: GASTOS FINANCIEROS MES DE ABRIL BOGOTA TULUA | J14: GASTOS FINANCIEROS MES DE ABRIL BOGOTA TULUA | K14: BANCO DE BOGOTA | O14: =+MONTH(H14) -> 4 | P14: =+YEAR(H14) -> 2024 | Q14: =+VLOOKUP(O14,'COMISIONES ENERO-MARZO 2025 (2)'!$X:$Y,2,0) -> Abril
... C526: 5305 - DEL SECTOR FINANCIERO | D526: 53059501 | E526: IMPUESTO 4 X 1.000 | F526: 1851230.9 | G526: NIB-00008386 | H526: 46022 | I526: GASTOS BANCARIOS FONDO INVERSION RENTA L 482800029407 DAV MES DE DICIEMBRE 2025 | J526: GASTOS BANCARIOS FONDO INVERSION RENTA L 482800029407 DAV MES DE DICIEMBRE 2025 | K526: PATRIMONIOS AUTONOMOS ADMINISTRADOS POR LA SOC FIDUCIARIA DAVIVIENDA | O526: =+MONTH(H526) -> 12 | P526: =+YEAR(H526) -> 2025 | Q526: =+VLOOKUP(O526,'COMISIONES ENERO-MARZO 2025 (2)'!$X:$Y,2,0) -> Diciembre
C527: 5305 - DEL SECTOR FINANCIERO | D527: 53059501 | E527: IMPUESTO 4 X 1.000 | F527: 1433841 | G527: NIB-00008424 | H527: 46022 | I527: GASTOS BANCARIOS BANCO BBVA COLOMBIA CTE MES DE DICIEMBRE 2025 | J527: GASTOS BANCARIOS BANCO BBVA COLOMBIA CTE MES DE DICIEMBRE 2025 | K527: BBVA COLOMBIA S.A. | O527: 12 | P527: 2025 | Q527: Diciembre
C528: 5305 - DEL SECTOR FINANCIERO | D528: 53059501 | E528: IMPUESTO 4 X 1.000 | F528: 974938.82 | G528: NIB-00008368 | H528: 46022 | I528: GASTOS BANCARIOS BANCO POPULAR CTA CTE 110560212276 MES DE DICIEMBRE 2025 | J528: GASTOS BANCARIOS BANCO POPULAR CTA CTE 110560212276 MES DE DICIEMBRE 2025 | K528: BANCO POPULAR | O528: =+MONTH(H528) -> 12 | P528: =+YEAR(H528) -> 2025 | Q528: =+VLOOKUP(O528,'COMISIONES ENERO-MARZO 2025 (2)'!$X:$Y,2,0) -> Diciembre
C529: 5305 - DEL SECTOR FINANCIERO | D529: 53059501 | E529: IMPUESTO 4 X 1.000 | F529: =757704.24+29231.13 -> 786935.37 | G529: NIB-00008364 | H529: 46022 | I529: GASTOS BANCARIOS BANCOLOMBIA AHORRO 30631513979 | J529: GASTOS BANCARIOS BANCOLOMBIA AHORRO 30631513979 | K529: BANCOLOMBIA | O529: =+MONTH(H529) -> 12 | P529: =+YEAR(H529) -> 2025 | Q529: =+VLOOKUP(O529,'COMISIONES ENERO-MARZO 2025 (2)'!$X:$Y,2,0) -> Diciembre
C530: 5305 - DEL SECTOR FINANCIERO | D530: 53050501 | E530: GASTOS BANCARIOS | F530: 168067.23 | G530: NIB-00008326 | H530: 46006 | I530: FACTORING FAN-33227 COMISION PAGO | J530: FACTORING FAN-33227 COMISION PAGO | K530: KLYM S.A.S | O530: =+MONTH(H530) -> 12 | P530: =+YEAR(H530) -> 2025 | Q530: =+VLOOKUP(O530,'COMISIONES ENERO-MARZO 2025 (2)'!$X:$Y,2,0) -> Diciembre
C531: 5305 - DEL SECTOR FINANCIERO | D531: 53059501 | E531: IMPUESTO 4 X 1.000 | F531: 24471.84 | G531: NIB-00008366 | H531: 46022 | I531: GASTOS BANCARIOS BANCOLOMBIA SOBREGIRO 76282316703 MES DE DICIEMBRE 2025 | J531: GASTOS BANCARIOS BANCOLOMBIA SOBREGIRO 76282316703 MES DE DICIEMBRE 2025 | K531: BANCOLOMBIA | O531: =+MONTH(H531) -> 12 | P531: =+YEAR(H531) -> 2025 | Q531: =+VLOOKUP(O531,'COMISIONES ENERO-MARZO 2025 (2)'!$X:$Y,2,0) -> Diciembre
C532: 5305 - DEL SECTOR FINANCIERO | D532: 53059501 | E532: IMPUESTO 4 X 1.000 | F532: 23906 | G532: NIB-00008363 | H532: 46000 | I532: LEGALIZACION DE TC DESTINOS 4302840001596798 MES DE NOVIEMBRE 2025 | J532: LEGALIZACION DE TC DESTINOS 4302840001596798 MES DE NOVIEMBRE 2025 | K532: BANCO DE BOGOTA | O532: =+MONTH(H532) -> 12 | P532: =+YEAR(H532) -> 2025 | Q532: =+VLOOKUP(O532,'COMISIONES ENERO-MARZO 2025 (2)'!$X:$Y,2,0) -> Diciembre
C533: 5305 - DEL SECTOR FINANCIERO | D533: 53059501 | E533: IMPUESTO 4 X 1.000 | F533: 20123 | G533: NIB-00008372 | H533: 46022 | I533: GASTOS BANCARIOS BANCO DE BOGOTA SOBREGIRO 484183223 MES DE DICIEMBRE 2025 | J533: GASTOS BANCARIOS BANCO DE BOGOTA SOBREGIRO 484183223 MES DE DICIEMBRE 2025 | K533: BANCO DE BOGOTA | O533: =+MONTH(H533) -> 12 | P533: =+YEAR(H533) -> 2025 | Q533: =+VLOOKUP(O533,'COMISIONES ENERO-MARZO 2025 (2)'!$X:$Y,2,0) -> Diciembre
C534: 5305 - DEL SECTOR FINANCIERO | D534: 53059501 | E534: IMPUESTO 4 X 1.000 | F534: 11913.6 | G534: NIP-00018159 | H534: 46022 | I534: contabilizacion iva comison 4*1000 | J534: contabilizacion iva comison 4*1000 | K534: BANCOLOMBIA | O534: =+MONTH(H534) -> 12 | P534: =+YEAR(H534) -> 2025 | Q534: =+VLOOKUP(O534,'COMISIONES ENERO-MARZO 2025 (2)'!$X:$Y,2,0) -> Diciembre
C535: 5305 - DEL SECTOR FINANCIERO | D535: 53059501 | E535: IMPUESTO 4 X 1.000 | F535: 11216.8 | G535: NIP-00018075 | H535: 46002 | I535: CONTABILIZAICON IVA COMISON 4*1000 | J535: CONTABILIZAICON IVA COMISON 4*1000 | K535: BANCOLOMBIA | O535: =+MONTH(H535) -> 12 | P535: =+YEAR(H535) -> 2025 | Q535: =+VLOOKUP(O535,'COMISIONES ENERO-MARZO 2025 (2)'!$X:$Y,2,0) -> Diciembre
C536: 5305 - DEL SECTOR FINANCIERO | D536: 53059501 | E536: IMPUESTO 4 X 1.000 | F536: 10288 | G536: NIB-00008371 | H536: 46022 | I536: GASTOS BANCARIOS BANCO BOGOTA CALI CTE 256096355 MES DE DICIEMBRE 2025 | J536: GASTOS BANCARIOS BANCO BOGOTA CALI CTE 256096355 MES DE DICIEMBRE 2025 | K536: BANCO DE BOGOTA | O536: =+MONTH(H536) -> 12 | P536: =+YEAR(H536) -> 2025 | Q536: =+VLOOKUP(O536,'COMISIONES ENERO-MARZO 2025 (2)'!$X:$Y,2,0) -> Diciembre
C537: 5305 - DEL SECTOR FINANCIERO | D537: 53059501 | E537: IMPUESTO 4 X 1.000 | F537: 7382 | G537: NIC-00039498 | H537: 46020 | I537: GG-FEV-32730-LEGALIZACIÓN TARJETA DE CRÉDITO DIRECCIÓN FINANCIERA # 5592 2520 9372 1520 OCTUBRE NOVIEMBRE | J537: GG-FEV-32730-LEGALIZACIÓN TARJETA DE CRÉDITO DIRECCIÓN FINANCIERA # 5592 2520 9372 1520 OCTUBRE NOVIEMBRE | K537: BANCO DAVIVIENDA S.A | O537: =+MONTH(H537) -> 12 | P537: =+YEAR(H537) -> 2025 | Q537: =+VLOOKUP(O537,'COMISIONES ENERO-MARZO 2025 (2)'!$X:$Y,2,0) -> Diciembre
C538: 5305 - DEL SECTOR FINANCIERO | D538: 53059501 | E538: IMPUESTO 4 X 1.000 | F538: 6416.8 | G538: NIP-00018142 | H538: 46014 | I538: CONTABILIZACION IVA COMISON 4*1000 | J538: CONTABILIZACION IVA COMISON 4*1000 | K538: BANCOLOMBIA | O538: =+MONTH(H538) -> 12 | P538: =+YEAR(H538) -> 2025 | Q538: =+VLOOKUP(O538,'COMISIONES ENERO-MARZO 2025 (2)'!$X:$Y,2,0) -> Diciembre
C539: 5305 - DEL SECTOR FINANCIERO | D539: 53059501 | E539: IMPUESTO 4 X 1.000 | F539: 5656.8 | G539: NIP-00018033 | H539: 45993 | I539: CONTABILIZACION IVA COMISON 4*1000 | J539: CONTABILIZACION IVA COMISON 4*1000 | K539: BANCOLOMBIA | O539: =+MONTH(H539) -> 12 | P539: =+YEAR(H539) -> 2025 | Q539: =+VLOOKUP(O539,'COMISIONES ENERO-MARZO 2025 (2)'!$X:$Y,2,0) -> Diciembre
C540: 5305 - DEL SECTOR FINANCIERO | D540: 53059501 | E540: IMPUESTO 4 X 1.000 | F540: 5259.8 | G540: NIB-00008410 | H540: 46022 | I540: TRASLADO DE FONDOS PARA PAGO DE FACTURA AFE846 ASOCACION DE FUNDACIONES FAMILIARES Y EMPRESARIALES - FUNDACION CARMELITA | J540: TRASLADO DE FONDOS PARA PAGO DE FACTURA AFE846 ASOCACION DE FUNDACIONES FAMILIARES Y EMPRESARIALES - FUNDACION CARMELITA | K540: BANCOLOMBIA | O540: =+MONTH(H540) -> 12 | P540: =+YEAR(H540) -> 2025 | Q540: =+VLOOKUP(O540,'COMISIONES ENERO-MARZO 2025 (2)'!$X:$Y,2,0) -> Diciembre
C541: 5305 - DEL SECTOR FINANCIERO | D541: 53059501 | E541: IMPUESTO 4 X 1.000 | F541: 4896.8 | G541: NIP-00018037 | H541: 45994 | I541: contabilizacion iva comison 4*1000 | J541: contabilizacion iva comison 4*1000 | K541: BANCOLOMBIA | O541: =+MONTH(H541) -> 12 | P541: =+YEAR(H541) -> 2025 | Q541: =+VLOOKUP(O541,'COMISIONES ENERO-MARZO 2025 (2)'!$X:$Y,2,0) -> Diciembre
... C566: 5305 - DEL SECTOR FINANCIERO | D566: 53059501 | E566: IMPUESTO 4 X 1.000 | F566: 2659 | G566: NIP-00018050 | H566: 45991 | I566: LEGALIZACIÓN TARJETA DE CREDITO DIRECCIÓN FINANCIERA SEPTIEMBRE OCTUBRE # 5592 2520 9372 1520 | J566: LEGALIZACIÓN TARJETA DE CREDITO DIRECCIÓN FINANCIERA SEPTIEMBRE OCTUBRE # 5592 2520 9372 1520 | K566: BANCO DAVIVIENDA S.A | O566: =+MONTH(H566) -> 11 | P566: =+YEAR(H566) -> 2025 | Q566: =+VLOOKUP(O566,'COMISIONES ENERO-MARZO 2025 (2)'!$X:$Y,2,0) -> Noviembre
F568: =+F570-F569 -> 29231.13
F569: 1.2677561e+08
F570: 1.2680484e+08

Sheet datos
